{"suggestions":[{"value":"68001 <span class='zip-desc'>Abie, Neb.</span>","data":{"lat":"41.3479","lon":"-96.9563"}},{"value":"68002 <span class='zip-desc'>Arlington, Neb.</span>","data":{"lat":"41.4417","lon":"-96.307"}},{"value":"68003 <span class='zip-desc'>Ashland, Neb.</span>","data":{"lat":"41.0541","lon":"-96.3904"}},{"value":"68004 <span class='zip-desc'>Bancroft, Neb.</span>","data":{"lat":"42.0267","lon":"-96.6171"}},{"value":"68005 <span class='zip-desc'>Bellevue, Neb.</span>","data":{"lat":"41.1497","lon":"-95.9099"}},{"value":"68007 <span class='zip-desc'>Bennington, Neb.</span>","data":{"lat":"41.3623","lon":"-96.1575"}},{"value":"68008 <span class='zip-desc'>Blair, Neb.</span>","data":{"lat":"41.5454","lon":"-96.1617"}},{"value":"68009 <span class='zip-desc'>Blair, Neb.</span>","data":{"lat":"41.5383","lon":"-96.1823"}},{"value":"68010 <span class='zip-desc'>Boys Town, Neb.</span>","data":{"lat":"41.2587","lon":"-96.133"}},{"value":"68014 <span class='zip-desc'>Bruno, Neb.</span>","data":{"lat":"41.2718","lon":"-96.9646"}},{"value":"68015 <span class='zip-desc'>Cedar Bluffs, Neb.</span>","data":{"lat":"41.3835","lon":"-96.5691"}},{"value":"68016 <span class='zip-desc'>Cedar Creek, Neb.</span>","data":{"lat":"41.0425","lon":"-96.1044"}},{"value":"68017 <span class='zip-desc'>Ceresco, Neb.</span>","data":{"lat":"41.0681","lon":"-96.6398"}},{"value":"68018 <span class='zip-desc'>Colon, Neb.</span>","data":{"lat":"41.2883","lon":"-96.6141"}},{"value":"68019 <span class='zip-desc'>Craig, Neb.</span>","data":{"lat":"41.7715","lon":"-96.3924"}},{"value":"68020 <span class='zip-desc'>Decatur, Neb.</span>","data":{"lat":"41.9966","lon":"-96.2595"}},{"value":"68022 <span class='zip-desc'>Elkhorn, Neb.</span>","data":{"lat":"41.2756","lon":"-96.2431"}},{"value":"68023 <span class='zip-desc'>Fort Calhoun, Neb.</span>","data":{"lat":"41.4373","lon":"-96.0324"}},{"value":"68025 <span class='zip-desc'>Fremont, Neb.</span>","data":{"lat":"41.4416","lon":"-96.4945"}},{"value":"68026 <span class='zip-desc'>Fremont, Neb.</span>","data":{"lat":"41.5679","lon":"-96.6174"}},{"value":"68028 <span class='zip-desc'>Gretna, Neb.</span>","data":{"lat":"41.1345","lon":"-96.2458"}},{"value":"68029 <span class='zip-desc'>Herman, Neb.</span>","data":{"lat":"41.6524","lon":"-96.2869"}},{"value":"68030 <span class='zip-desc'>Homer, Neb.</span>","data":{"lat":"42.3322","lon":"-96.4656"}},{"value":"68031 <span class='zip-desc'>Hooper, Neb.</span>","data":{"lat":"41.6414","lon":"-96.5232"}},{"value":"68033 <span class='zip-desc'>Ithaca, Neb.</span>","data":{"lat":"41.1748","lon":"-96.5298"}},{"value":"68034 <span class='zip-desc'>Kennard, Neb.</span>","data":{"lat":"41.4526","lon":"-96.1903"}},{"value":"68035 <span class='zip-desc'>Leshara, Neb.</span>","data":{"lat":"41.3394","lon":"-96.4448"}},{"value":"68036 <span class='zip-desc'>Linwood, Neb.</span>","data":{"lat":"41.4129","lon":"-96.9399"}},{"value":"68037 <span class='zip-desc'>Louisville, Neb.</span>","data":{"lat":"40.9967","lon":"-96.1948"}},{"value":"68038 <span class='zip-desc'>Lyons, Neb.</span>","data":{"lat":"41.9442","lon":"-96.4661"}},{"value":"68039 <span class='zip-desc'>Macy, Neb.</span>","data":{"lat":"42.1177","lon":"-96.3589"}},{"value":"68040 <span class='zip-desc'>Malmo, Neb.</span>","data":{"lat":"41.2984","lon":"-96.7327"}},{"value":"68041 <span class='zip-desc'>Mead, Neb.</span>","data":{"lat":"41.2393","lon":"-96.4961"}},{"value":"68042 <span class='zip-desc'>Memphis, Neb.</span>","data":{"lat":"41.0946","lon":"-96.4306"}},{"value":"68044 <span class='zip-desc'>Nickerson, Neb.</span>","data":{"lat":"41.5491","lon":"-96.4441"}},{"value":"68045 <span class='zip-desc'>Oakland, Neb.</span>","data":{"lat":"41.8384","lon":"-96.4671"}},{"value":"68046 <span class='zip-desc'>Papillion, Neb.</span>","data":{"lat":"41.1523","lon":"-96.0371"}},{"value":"68047 <span class='zip-desc'>Pender, Neb.</span>","data":{"lat":"42.1177","lon":"-96.7189"}},{"value":"68048 <span class='zip-desc'>Plattsmouth, Neb.</span>","data":{"lat":"40.9992","lon":"-95.9139"}},{"value":"68050 <span class='zip-desc'>Prague, Neb.</span>","data":{"lat":"41.3036","lon":"-96.8301"}},{"value":"68054 <span class='zip-desc'>Richfield, Neb.</span>","data":{"lat":"41.089","lon":"-96.0704"}},{"value":"68055 <span class='zip-desc'>Rosalie, Neb.</span>","data":{"lat":"42.0574","lon":"-96.4929"}},{"value":"68056 <span class='zip-desc'>St Columbans, Neb.</span>","data":{"lat":"41.0927","lon":"-96.0905"}},{"value":"68057 <span class='zip-desc'>Scribner, Neb.</span>","data":{"lat":"41.663","lon":"-96.6441"}},{"value":"68058 <span class='zip-desc'>South Bend, Neb.</span>","data":{"lat":"41.0067","lon":"-96.2462"}},{"value":"68059 <span class='zip-desc'>Springfield, Neb.</span>","data":{"lat":"41.0765","lon":"-96.1438"}},{"value":"68061 <span class='zip-desc'>Tekamah, Neb.</span>","data":{"lat":"41.7819","lon":"-96.2281"}},{"value":"68062 <span class='zip-desc'>Thurston, Neb.</span>","data":{"lat":"42.1882","lon":"-96.6904"}},{"value":"68063 <span class='zip-desc'>Uehling, Neb.</span>","data":{"lat":"41.7369","lon":"-96.5037"}},{"value":"68064 <span class='zip-desc'>Valley, Neb.</span>","data":{"lat":"41.3186","lon":"-96.3463"}},{"value":"68065 <span class='zip-desc'>Valparaiso, Neb.</span>","data":{"lat":"41.0843","lon":"-96.8091"}},{"value":"68066 <span class='zip-desc'>Wahoo, Neb.</span>","data":{"lat":"41.2117","lon":"-96.6219"}},{"value":"68067 <span class='zip-desc'>Walthill, Neb.</span>","data":{"lat":"42.1485","lon":"-96.4803"}},{"value":"68068 <span class='zip-desc'>Washington, Neb.</span>","data":{"lat":"41.3953","lon":"-96.209"}},{"value":"68069 <span class='zip-desc'>Waterloo, Neb.</span>","data":{"lat":"41.2702","lon":"-96.3063"}},{"value":"68070 <span class='zip-desc'>Weston, Neb.</span>","data":{"lat":"41.1811","lon":"-96.7691"}},{"value":"68071 <span class='zip-desc'>Winnebago, Neb.</span>","data":{"lat":"42.2339","lon":"-96.4685"}},{"value":"68072 <span class='zip-desc'>Winslow, Neb.</span>","data":{"lat":"41.6102","lon":"-96.5033"}},{"value":"68073 <span class='zip-desc'>Yutan, Neb.</span>","data":{"lat":"41.234","lon":"-96.3932"}},{"value":"68101 <span class='zip-desc'>Omaha, Neb.</span>","data":{"lat":"41.2917","lon":"-96.1711"}},{"value":"68102 <span class='zip-desc'>Omaha, Neb.</span>","data":{"lat":"41.259","lon":"-95.9409"}},{"value":"68103 <span class='zip-desc'>Omaha, Neb.</span>","data":{"lat":"41.2917","lon":"-96.1711"}},{"value":"68104 <span class='zip-desc'>Omaha, Neb.</span>","data":{"lat":"41.2919","lon":"-95.9999"}},{"value":"68105 <span class='zip-desc'>Omaha, Neb.</span>","data":{"lat":"41.2435","lon":"-95.9629"}},{"value":"68106 <span class='zip-desc'>Omaha, Neb.</span>","data":{"lat":"41.2403","lon":"-95.998"}},{"value":"68107 <span class='zip-desc'>Omaha, Neb.</span>","data":{"lat":"41.2068","lon":"-95.9559"}},{"value":"68108 <span class='zip-desc'>Omaha, Neb.</span>","data":{"lat":"41.2382","lon":"-95.9336"}},{"value":"68109 <span class='zip-desc'>Omaha, Neb.</span>","data":{"lat":"41.2917","lon":"-96.1711"}},{"value":"68110 <span class='zip-desc'>Omaha, Neb.</span>","data":{"lat":"41.2933","lon":"-95.9361"}},{"value":"68111 <span class='zip-desc'>Omaha, Neb.</span>","data":{"lat":"41.2962","lon":"-95.965"}},{"value":"68112 <span class='zip-desc'>Omaha, Neb.</span>","data":{"lat":"41.3296","lon":"-95.9597"}},{"value":"68113 <span class='zip-desc'>Offutt A F B, Neb.</span>","data":{"lat":"41.1148","lon":"-95.9076"}},{"value":"68114 <span class='zip-desc'>Omaha, Neb.</span>","data":{"lat":"41.2656","lon":"-96.0493"}},{"value":"68116 <span class='zip-desc'>Omaha, Neb.</span>","data":{"lat":"41.2879","lon":"-96.1495"}},{"value":"68117 <span class='zip-desc'>Omaha, Neb.</span>","data":{"lat":"41.2064","lon":"-95.9953"}},{"value":"68118 <span class='zip-desc'>Omaha, Neb.</span>","data":{"lat":"41.2606","lon":"-96.1661"}},{"value":"68119 <span class='zip-desc'>Omaha, Neb.</span>","data":{"lat":"41.2917","lon":"-96.1711"}},{"value":"68120 <span class='zip-desc'>Omaha, Neb.</span>","data":{"lat":"41.2917","lon":"-96.1711"}},{"value":"68122 <span class='zip-desc'>Omaha, Neb.</span>","data":{"lat":"41.3333","lon":"-96.0458"}},{"value":"68123 <span class='zip-desc'>Bellevue, Neb.</span>","data":{"lat":"41.1156","lon":"-95.9393"}},{"value":"68124 <span class='zip-desc'>Omaha, Neb.</span>","data":{"lat":"41.2338","lon":"-96.0495"}},{"value":"68127 <span class='zip-desc'>Omaha, Neb.</span>","data":{"lat":"41.2074","lon":"-96.0612"}},{"value":"68128 <span class='zip-desc'>La Vista, Neb.</span>","data":{"lat":"41.1814","lon":"-96.0658"}},{"value":"68130 <span class='zip-desc'>Omaha, Neb.</span>","data":{"lat":"41.2355","lon":"-96.1688"}},{"value":"68131 <span class='zip-desc'>Omaha, Neb.</span>","data":{"lat":"41.2647","lon":"-95.9639"}},{"value":"68132 <span class='zip-desc'>Omaha, Neb.</span>","data":{"lat":"41.2657","lon":"-95.996"}},{"value":"68133 <span class='zip-desc'>Papillion, Neb.</span>","data":{"lat":"41.1416","lon":"-96.0131"}},{"value":"68134 <span class='zip-desc'>Omaha, Neb.</span>","data":{"lat":"41.2949","lon":"-96.0546"}},{"value":"68135 <span class='zip-desc'>Omaha, Neb.</span>","data":{"lat":"41.2104","lon":"-96.1698"}},{"value":"68136 <span class='zip-desc'>Omaha, Neb.</span>","data":{"lat":"41.1683","lon":"-96.2096"}},{"value":"68137 <span class='zip-desc'>Omaha, Neb.</span>","data":{"lat":"41.2075","lon":"-96.1147"}},{"value":"68138 <span class='zip-desc'>Omaha, Neb.</span>","data":{"lat":"41.1549","lon":"-96.1376"}},{"value":"68139 <span class='zip-desc'>Omaha, Neb.</span>","data":{"lat":"41.2917","lon":"-96.1711"}},{"value":"68142 <span class='zip-desc'>Omaha, Neb.</span>","data":{"lat":"41.3359","lon":"-96.0901"}},{"value":"68144 <span class='zip-desc'>Omaha, Neb.</span>","data":{"lat":"41.2335","lon":"-96.1188"}},{"value":"68145 <span class='zip-desc'>Omaha, Neb.</span>","data":{"lat":"41.2917","lon":"-96.1711"}},{"value":"68147 <span class='zip-desc'>Bellevue, Neb.</span>","data":{"lat":"41.1758","lon":"-95.9553"}},{"value":"68152 <span class='zip-desc'>Omaha, Neb.</span>","data":{"lat":"41.3346","lon":"-96.0003"}},{"value":"68154 <span class='zip-desc'>Omaha, Neb.</span>","data":{"lat":"41.2642","lon":"-96.1206"}},{"value":"68155 <span class='zip-desc'>Omaha, Neb.</span>","data":{"lat":"41.2917","lon":"-96.1711"}},{"value":"68157 <span class='zip-desc'>Omaha, Neb.</span>","data":{"lat":"41.181","lon":"-95.9909"}},{"value":"68164 <span class='zip-desc'>Omaha, Neb.</span>","data":{"lat":"41.2955","lon":"-96.1008"}},{"value":"68172 <span class='zip-desc'>Omaha, Neb.</span>","data":{"lat":"41.2917","lon":"-96.1711"}},{"value":"68175 <span class='zip-desc'>Omaha, Neb.</span>","data":{"lat":"41.2917","lon":"-96.1711"}},{"value":"68176 <span class='zip-desc'>Omaha, Neb.</span>","data":{"lat":"41.2917","lon":"-96.1711"}},{"value":"68178 <span class='zip-desc'>Omaha, Neb.</span>","data":{"lat":"41.2657","lon":"-95.9477"}},{"value":"68179 <span class='zip-desc'>Omaha, Neb.</span>","data":{"lat":"41.2917","lon":"-96.1711"}},{"value":"68180 <span class='zip-desc'>Omaha, Neb.</span>","data":{"lat":"41.2917","lon":"-96.1711"}},{"value":"68181 <span class='zip-desc'>Omaha, Neb.</span>","data":{"lat":"41.2917","lon":"-96.1711"}},{"value":"68182 <span class='zip-desc'>Omaha, Neb.</span>","data":{"lat":"41.2917","lon":"-96.1711"}},{"value":"68183 <span class='zip-desc'>Omaha, Neb.</span>","data":{"lat":"41.2917","lon":"-96.1711"}},{"value":"68197 <span class='zip-desc'>Omaha, Neb.</span>","data":{"lat":"41.249","lon":"-96.0274"}},{"value":"68198 <span class='zip-desc'>Omaha, Neb.</span>","data":{"lat":"41.2917","lon":"-96.1711"}},{"value":"68301 <span class='zip-desc'>Adams, Neb.</span>","data":{"lat":"40.4576","lon":"-96.5396"}},{"value":"68303 <span class='zip-desc'>Alexandria, Neb.</span>","data":{"lat":"40.2614","lon":"-97.4039"}},{"value":"68304 <span class='zip-desc'>Alvo, Neb.</span>","data":{"lat":"40.8992","lon":"-96.4036"}},{"value":"68305 <span class='zip-desc'>Auburn, Neb.</span>","data":{"lat":"40.3789","lon":"-95.8526"}},{"value":"68307 <span class='zip-desc'>Avoca, Neb.</span>","data":{"lat":"40.8159","lon":"-96.0957"}},{"value":"68309 <span class='zip-desc'>Barneston, Neb.</span>","data":{"lat":"40.0412","lon":"-96.5963"}},{"value":"68310 <span class='zip-desc'>Beatrice, Neb.</span>","data":{"lat":"40.2705","lon":"-96.7435"}},{"value":"68313 <span class='zip-desc'>Beaver Crossing, Neb.</span>","data":{"lat":"40.7887","lon":"-97.2914"}},{"value":"68314 <span class='zip-desc'>Bee, Neb.</span>","data":{"lat":"41.0007","lon":"-97.0745"}},{"value":"68315 <span class='zip-desc'>Belvidere, Neb.</span>","data":{"lat":"40.251","lon":"-97.5554"}},{"value":"68316 <span class='zip-desc'>Benedict, Neb.</span>","data":{"lat":"41.0033","lon":"-97.6029"}},{"value":"68317 <span class='zip-desc'>Bennet, Neb.</span>","data":{"lat":"40.6382","lon":"-96.5134"}},{"value":"68318 <span class='zip-desc'>Blue Springs, Neb.</span>","data":{"lat":"40.1407","lon":"-96.659"}},{"value":"68319 <span class='zip-desc'>Bradshaw, Neb.</span>","data":{"lat":"40.9207","lon":"-97.7607"}},{"value":"68320 <span class='zip-desc'>Brock, Neb.</span>","data":{"lat":"40.4772","lon":"-95.9801"}},{"value":"68321 <span class='zip-desc'>Brownville, Neb.</span>","data":{"lat":"40.3994","lon":"-95.6935"}},{"value":"68322 <span class='zip-desc'>Bruning, Neb.</span>","data":{"lat":"40.3302","lon":"-97.5573"}},{"value":"68323 <span class='zip-desc'>Burchard, Neb.</span>","data":{"lat":"40.1057","lon":"-96.3488"}},{"value":"68324 <span class='zip-desc'>Burr, Neb.</span>","data":{"lat":"40.5601","lon":"-96.2384"}},{"value":"68325 <span class='zip-desc'>Byron, Neb.</span>","data":{"lat":"40.0269","lon":"-97.7612"}},{"value":"68326 <span class='zip-desc'>Carleton, Neb.</span>","data":{"lat":"40.3005","lon":"-97.6719"}},{"value":"68327 <span class='zip-desc'>Chester, Neb.</span>","data":{"lat":"40.029","lon":"-97.6197"}},{"value":"68328 <span class='zip-desc'>Clatonia, Neb.</span>","data":{"lat":"40.4724","lon":"-96.8555"}},{"value":"68329 <span class='zip-desc'>Cook, Neb.</span>","data":{"lat":"40.4986","lon":"-96.1526"}},{"value":"68330 <span class='zip-desc'>Cordova, Neb.</span>","data":{"lat":"40.7185","lon":"-97.3407"}},{"value":"68331 <span class='zip-desc'>Cortland, Neb.</span>","data":{"lat":"40.4976","lon":"-96.7166"}},{"value":"68332 <span class='zip-desc'>Crab Orchard, Neb.</span>","data":{"lat":"40.3166","lon":"-96.4116"}},{"value":"68333 <span class='zip-desc'>Crete, Neb.</span>","data":{"lat":"40.6193","lon":"-96.9567"}},{"value":"68335 <span class='zip-desc'>Davenport, Neb.</span>","data":{"lat":"40.3108","lon":"-97.805"}},{"value":"68336 <span class='zip-desc'>Davey, Neb.</span>","data":{"lat":"40.9639","lon":"-96.688"}},{"value":"68337 <span class='zip-desc'>Dawson, Neb.</span>","data":{"lat":"40.1377","lon":"-95.8341"}},{"value":"68338 <span class='zip-desc'>Daykin, Neb.</span>","data":{"lat":"40.3192","lon":"-97.3043"}},{"value":"68339 <span class='zip-desc'>Denton, Neb.</span>","data":{"lat":"40.7009","lon":"-96.8532"}},{"value":"68340 <span class='zip-desc'>Deshler, Neb.</span>","data":{"lat":"40.1387","lon":"-97.73"}},{"value":"68341 <span class='zip-desc'>De Witt, Neb.</span>","data":{"lat":"40.3944","lon":"-96.9338"}},{"value":"68342 <span class='zip-desc'>Diller, Neb.</span>","data":{"lat":"40.1192","lon":"-96.9495"}},{"value":"68343 <span class='zip-desc'>Dorchester, Neb.</span>","data":{"lat":"40.6499","lon":"-97.1056"}},{"value":"68344 <span class='zip-desc'>Douglas, Neb.</span>","data":{"lat":"40.5838","lon":"-96.397"}},{"value":"68345 <span class='zip-desc'>Du Bois, Neb.</span>","data":{"lat":"40.0375","lon":"-96.0575"}},{"value":"68346 <span class='zip-desc'>Dunbar, Neb.</span>","data":{"lat":"40.6592","lon":"-96.0136"}},{"value":"68347 <span class='zip-desc'>Eagle, Neb.</span>","data":{"lat":"40.8169","lon":"-96.429"}},{"value":"68348 <span class='zip-desc'>Elk Creek, Neb.</span>","data":{"lat":"40.2977","lon":"-96.1421"}},{"value":"68349 <span class='zip-desc'>Elmwood, Neb.</span>","data":{"lat":"40.8378","lon":"-96.2944"}},{"value":"68350 <span class='zip-desc'>Endicott, Neb.</span>","data":{"lat":"40.0496","lon":"-97.0813"}},{"value":"68351 <span class='zip-desc'>Exeter, Neb.</span>","data":{"lat":"40.6341","lon":"-97.4424"}},{"value":"68352 <span class='zip-desc'>Fairbury, Neb.</span>","data":{"lat":"40.1488","lon":"-97.1839"}},{"value":"68354 <span class='zip-desc'>Fairmont, Neb.</span>","data":{"lat":"40.6404","lon":"-97.5873"}},{"value":"68355 <span class='zip-desc'>Falls City, Neb.</span>","data":{"lat":"40.0742","lon":"-95.5931"}},{"value":"68357 <span class='zip-desc'>Filley, Neb.</span>","data":{"lat":"40.2946","lon":"-96.5301"}},{"value":"68358 <span class='zip-desc'>Firth, Neb.</span>","data":{"lat":"40.5586","lon":"-96.614"}},{"value":"68359 <span class='zip-desc'>Friend, Neb.</span>","data":{"lat":"40.6368","lon":"-97.2739"}},{"value":"68360 <span class='zip-desc'>Garland, Neb.</span>","data":{"lat":"40.9412","lon":"-96.9702"}},{"value":"68361 <span class='zip-desc'>Geneva, Neb.</span>","data":{"lat":"40.5277","lon":"-97.6096"}},{"value":"68362 <span class='zip-desc'>Gilead, Neb.</span>","data":{"lat":"40.147","lon":"-97.4271"}},{"value":"68364 <span class='zip-desc'>Goehner, Neb.</span>","data":{"lat":"40.8291","lon":"-97.1967"}},{"value":"68365 <span class='zip-desc'>Grafton, Neb.</span>","data":{"lat":"40.6402","lon":"-97.7403"}},{"value":"68366 <span class='zip-desc'>Greenwood, Neb.</span>","data":{"lat":"40.9706","lon":"-96.4258"}},{"value":"68367 <span class='zip-desc'>Gresham, Neb.</span>","data":{"lat":"41.021","lon":"-97.4079"}},{"value":"68368 <span class='zip-desc'>Hallam, Neb.</span>","data":{"lat":"40.5739","lon":"-96.7998"}},{"value":"68370 <span class='zip-desc'>Hebron, Neb.</span>","data":{"lat":"40.1728","lon":"-97.6052"}},{"value":"68371 <span class='zip-desc'>Henderson, Neb.</span>","data":{"lat":"40.7814","lon":"-97.7979"}},{"value":"68372 <span class='zip-desc'>Hickman, Neb.</span>","data":{"lat":"40.6119","lon":"-96.6247"}},{"value":"68374 <span class='zip-desc'>Holmesville, Neb.</span>","data":{"lat":"40.2202","lon":"-96.6326"}},{"value":"68375 <span class='zip-desc'>Hubbell, Neb.</span>","data":{"lat":"40.0456","lon":"-97.4735"}},{"value":"68376 <span class='zip-desc'>Humboldt, Neb.</span>","data":{"lat":"40.1566","lon":"-95.9311"}},{"value":"68377 <span class='zip-desc'>Jansen, Neb.</span>","data":{"lat":"40.2074","lon":"-97.0244"}},{"value":"68378 <span class='zip-desc'>Johnson, Neb.</span>","data":{"lat":"40.4016","lon":"-95.9883"}},{"value":"68379 <span class='zip-desc'>Julian, Neb.</span>","data":{"lat":"40.5199","lon":"-95.8674"}},{"value":"68380 <span class='zip-desc'>Lewiston, Neb.</span>","data":{"lat":"40.2309","lon":"-96.4049"}},{"value":"68381 <span class='zip-desc'>Liberty, Neb.</span>","data":{"lat":"40.0801","lon":"-96.4804"}},{"value":"68382 <span class='zip-desc'>Lorton, Neb.</span>","data":{"lat":"40.5973","lon":"-96.0241"}},{"value":"68401 <span class='zip-desc'>Mc Cool Junction, Neb.</span>","data":{"lat":"40.7442","lon":"-97.5937"}},{"value":"68402 <span class='zip-desc'>Malcolm, Neb.</span>","data":{"lat":"40.9091","lon":"-96.86"}},{"value":"68403 <span class='zip-desc'>Manley, Neb.</span>","data":{"lat":"40.9207","lon":"-96.168"}},{"value":"68404 <span class='zip-desc'>Martell, Neb.</span>","data":{"lat":"40.6514","lon":"-96.7442"}},{"value":"68405 <span class='zip-desc'>Milford, Neb.</span>","data":{"lat":"40.7632","lon":"-97.0576"}},{"value":"68406 <span class='zip-desc'>Milligan, Neb.</span>","data":{"lat":"40.4952","lon":"-97.3997"}},{"value":"68407 <span class='zip-desc'>Murdock, Neb.</span>","data":{"lat":"40.919","lon":"-96.2848"}},{"value":"68409 <span class='zip-desc'>Murray, Neb.</span>","data":{"lat":"40.92","lon":"-95.9227"}},{"value":"68410 <span class='zip-desc'>Nebraska City, Neb.</span>","data":{"lat":"40.6747","lon":"-95.8619"}},{"value":"68413 <span class='zip-desc'>Nehawka, Neb.</span>","data":{"lat":"40.833","lon":"-95.993"}},{"value":"68414 <span class='zip-desc'>Nemaha, Neb.</span>","data":{"lat":"40.3198","lon":"-95.6913"}},{"value":"68415 <span class='zip-desc'>Odell, Neb.</span>","data":{"lat":"40.0451","lon":"-96.8019"}},{"value":"68416 <span class='zip-desc'>Ohiowa, Neb.</span>","data":{"lat":"40.4065","lon":"-97.4427"}},{"value":"68417 <span class='zip-desc'>Otoe, Neb.</span>","data":{"lat":"40.7355","lon":"-96.1329"}},{"value":"68418 <span class='zip-desc'>Palmyra, Neb.</span>","data":{"lat":"40.705","lon":"-96.3999"}},{"value":"68419 <span class='zip-desc'>Panama, Neb.</span>","data":{"lat":"40.5998","lon":"-96.5129"}},{"value":"68420 <span class='zip-desc'>Pawnee City, Neb.</span>","data":{"lat":"40.1093","lon":"-96.1509"}},{"value":"68421 <span class='zip-desc'>Peru, Neb.</span>","data":{"lat":"40.4766","lon":"-95.7312"}},{"value":"68422 <span class='zip-desc'>Pickrell, Neb.</span>","data":{"lat":"40.3821","lon":"-96.7344"}},{"value":"68423 <span class='zip-desc'>Pleasant Dale, Neb.</span>","data":{"lat":"40.8133","lon":"-96.9513"}},{"value":"68424 <span class='zip-desc'>Plymouth, Neb.</span>","data":{"lat":"40.3039","lon":"-97.0012"}},{"value":"68428 <span class='zip-desc'>Raymond, Neb.</span>","data":{"lat":"40.9342","lon":"-96.7866"}},{"value":"68429 <span class='zip-desc'>Reynolds, Neb.</span>","data":{"lat":"40.0598","lon":"-97.3806"}},{"value":"68430 <span class='zip-desc'>Roca, Neb.</span>","data":{"lat":"40.6702","lon":"-96.6391"}},{"value":"68431 <span class='zip-desc'>Rulo, Neb.</span>","data":{"lat":"40.0536","lon":"-95.4292"}},{"value":"68432 <span class='zip-desc'>Saint Mary, Neb.</span>","data":{"lat":"40.4448","lon":"-96.29"}},{"value":"68433 <span class='zip-desc'>Salem, Neb.</span>","data":{"lat":"40.062","lon":"-95.7273"}},{"value":"68434 <span class='zip-desc'>Seward, Neb.</span>","data":{"lat":"40.9066","lon":"-97.0966"}},{"value":"68436 <span class='zip-desc'>Shickley, Neb.</span>","data":{"lat":"40.4077","lon":"-97.7143"}},{"value":"68437 <span class='zip-desc'>Shubert, Neb.</span>","data":{"lat":"40.2325","lon":"-95.6895"}},{"value":"68438 <span class='zip-desc'>Sprague, Neb.</span>","data":{"lat":"40.6267","lon":"-96.7456"}},{"value":"68439 <span class='zip-desc'>Staplehurst, Neb.</span>","data":{"lat":"40.9845","lon":"-97.1859"}},{"value":"68440 <span class='zip-desc'>Steele City, Neb.</span>","data":{"lat":"40.0425","lon":"-96.9907"}},{"value":"68441 <span class='zip-desc'>Steinauer, Neb.</span>","data":{"lat":"40.2169","lon":"-96.2302"}},{"value":"68442 <span class='zip-desc'>Stella, Neb.</span>","data":{"lat":"40.2303","lon":"-95.768"}},{"value":"68443 <span class='zip-desc'>Sterling, Neb.</span>","data":{"lat":"40.4637","lon":"-96.3867"}},{"value":"68444 <span class='zip-desc'>Strang, Neb.</span>","data":{"lat":"40.3981","lon":"-97.5521"}},{"value":"68445 <span class='zip-desc'>Swanton, Neb.</span>","data":{"lat":"40.3844","lon":"-97.0806"}},{"value":"68446 <span class='zip-desc'>Syracuse, Neb.</span>","data":{"lat":"40.6614","lon":"-96.1824"}},{"value":"68447 <span class='zip-desc'>Table Rock, Neb.</span>","data":{"lat":"40.1874","lon":"-96.0818"}},{"value":"68448 <span class='zip-desc'>Talmage, Neb.</span>","data":{"lat":"40.5586","lon":"-96.0138"}},{"value":"68450 <span class='zip-desc'>Tecumseh, Neb.</span>","data":{"lat":"40.3697","lon":"-96.205"}},{"value":"68452 <span class='zip-desc'>Ong, Neb.</span>","data":{"lat":"40.3968","lon":"-97.861"}},{"value":"68453 <span class='zip-desc'>Tobias, Neb.</span>","data":{"lat":"40.4262","lon":"-97.3184"}},{"value":"68454 <span class='zip-desc'>Unadilla, Neb.</span>","data":{"lat":"40.6917","lon":"-96.2825"}},{"value":"68455 <span class='zip-desc'>Union, Neb.</span>","data":{"lat":"40.8245","lon":"-95.9037"}},{"value":"68456 <span class='zip-desc'>Utica, Neb.</span>","data":{"lat":"40.9168","lon":"-97.3344"}},{"value":"68457 <span class='zip-desc'>Verdon, Neb.</span>","data":{"lat":"40.1425","lon":"-95.7162"}},{"value":"68458 <span class='zip-desc'>Virginia, Neb.</span>","data":{"lat":"40.2309","lon":"-96.5121"}},{"value":"68460 <span class='zip-desc'>Waco, Neb.</span>","data":{"lat":"40.9198","lon":"-97.4534"}},{"value":"68461 <span class='zip-desc'>Walton, Neb.</span>","data":{"lat":"40.7975","lon":"-96.5359"}},{"value":"68462 <span class='zip-desc'>Waverly, Neb.</span>","data":{"lat":"40.9222","lon":"-96.526"}},{"value":"68463 <span class='zip-desc'>Weeping Water, Neb.</span>","data":{"lat":"40.8731","lon":"-96.1528"}},{"value":"68464 <span class='zip-desc'>Western, Neb.</span>","data":{"lat":"40.4152","lon":"-97.1976"}},{"value":"68465 <span class='zip-desc'>Wilber, Neb.</span>","data":{"lat":"40.4821","lon":"-96.9757"}},{"value":"68466 <span class='zip-desc'>Wymore, Neb.</span>","data":{"lat":"40.113","lon":"-96.6613"}},{"value":"68467 <span class='zip-desc'>York, Neb.</span>","data":{"lat":"40.8667","lon":"-97.5825"}},{"value":"68501 <span class='zip-desc'>Lincoln, Neb.</span>","data":{"lat":"40.8651","lon":"-96.8231"}},{"value":"68502 <span class='zip-desc'>Lincoln, Neb.</span>","data":{"lat":"40.7893","lon":"-96.6938"}},{"value":"68503 <span class='zip-desc'>Lincoln, Neb.</span>","data":{"lat":"40.8233","lon":"-96.6766"}},{"value":"68504 <span class='zip-desc'>Lincoln, Neb.</span>","data":{"lat":"40.8392","lon":"-96.6532"}},{"value":"68505 <span class='zip-desc'>Lincoln, Neb.</span>","data":{"lat":"40.8247","lon":"-96.6252"}},{"value":"68506 <span class='zip-desc'>Lincoln, Neb.</span>","data":{"lat":"40.7848","lon":"-96.6431"}},{"value":"68507 <span class='zip-desc'>Lincoln, Neb.</span>","data":{"lat":"40.8473","lon":"-96.6289"}},{"value":"68508 <span class='zip-desc'>Lincoln, Neb.</span>","data":{"lat":"40.8145","lon":"-96.7009"}},{"value":"68509 <span class='zip-desc'>Lincoln, Neb.</span>","data":{"lat":"40.7845","lon":"-96.6888"}},{"value":"68510 <span class='zip-desc'>Lincoln, Neb.</span>","data":{"lat":"40.8063","lon":"-96.6545"}},{"value":"68511 <span class='zip-desc'>Lincoln, Neb.</span>","data":{"lat":"40.817","lon":"-96.7103"}},{"value":"68512 <span class='zip-desc'>Lincoln, Neb.</span>","data":{"lat":"40.7565","lon":"-96.6946"}},{"value":"68514 <span class='zip-desc'>Lincoln, Neb.</span>","data":{"lat":"40.9401","lon":"-96.6621"}},{"value":"68516 <span class='zip-desc'>Lincoln, Neb.</span>","data":{"lat":"40.7568","lon":"-96.6523"}},{"value":"68517 <span class='zip-desc'>Lincoln, Neb.</span>","data":{"lat":"40.9317","lon":"-96.6045"}},{"value":"68520 <span class='zip-desc'>Lincoln, Neb.</span>","data":{"lat":"40.7744","lon":"-96.5693"}},{"value":"68521 <span class='zip-desc'>Lincoln, Neb.</span>","data":{"lat":"40.851","lon":"-96.711"}},{"value":"68522 <span class='zip-desc'>Lincoln, Neb.</span>","data":{"lat":"40.7934","lon":"-96.7479"}},{"value":"68523 <span class='zip-desc'>Lincoln, Neb.</span>","data":{"lat":"40.7408","lon":"-96.7583"}},{"value":"68524 <span class='zip-desc'>Lincoln, Neb.</span>","data":{"lat":"40.8529","lon":"-96.7943"}},{"value":"68526 <span class='zip-desc'>Lincoln, Neb.</span>","data":{"lat":"40.7314","lon":"-96.5878"}},{"value":"68527 <span class='zip-desc'>Lincoln, Neb.</span>","data":{"lat":"40.8347","lon":"-96.5401"}},{"value":"68528 <span class='zip-desc'>Lincoln, Neb.</span>","data":{"lat":"40.8195","lon":"-96.7545"}},{"value":"68529 <span class='zip-desc'>Lincoln, Neb.</span>","data":{"lat":"40.8798","lon":"-96.7798"}},{"value":"68531 <span class='zip-desc'>Lincoln, Neb.</span>","data":{"lat":"40.9008","lon":"-96.7201"}},{"value":"68532 <span class='zip-desc'>Lincoln, Neb.</span>","data":{"lat":"40.7922","lon":"-96.8551"}},{"value":"68542 <span class='zip-desc'>Lincoln, Neb.</span>","data":{"lat":"40.7845","lon":"-96.6888"}},{"value":"68544 <span class='zip-desc'>Lincoln, Neb.</span>","data":{"lat":"40.7845","lon":"-96.6888"}},{"value":"68572 <span class='zip-desc'>Lincoln, Neb.</span>","data":{"lat":"40.7845","lon":"-96.6888"}},{"value":"68583 <span class='zip-desc'>Lincoln, Neb.</span>","data":{"lat":"40.7845","lon":"-96.6888"}},{"value":"68588 <span class='zip-desc'>Lincoln, Neb.</span>","data":{"lat":"40.8206","lon":"-96.6928"}},{"value":"68601 <span class='zip-desc'>Columbus, Neb.</span>","data":{"lat":"41.543","lon":"-97.3763"}},{"value":"68602 <span class='zip-desc'>Columbus, Neb.</span>","data":{"lat":"41.5381","lon":"-97.5418"}},{"value":"68620 <span class='zip-desc'>Albion, Neb.</span>","data":{"lat":"41.7049","lon":"-97.9991"}},{"value":"68621 <span class='zip-desc'>Ames, Neb.</span>","data":{"lat":"41.4613","lon":"-96.6463"}},{"value":"68622 <span class='zip-desc'>Bartlett, Neb.</span>","data":{"lat":"41.8697","lon":"-98.5567"}},{"value":"68623 <span class='zip-desc'>Belgrade, Neb.</span>","data":{"lat":"41.4611","lon":"-98.0866"}},{"value":"68624 <span class='zip-desc'>Bellwood, Neb.</span>","data":{"lat":"41.3474","lon":"-97.2747"}},{"value":"68626 <span class='zip-desc'>Brainard, Neb.</span>","data":{"lat":"41.1832","lon":"-96.9882"}},{"value":"68627 <span class='zip-desc'>Cedar Rapids, Neb.</span>","data":{"lat":"41.5564","lon":"-98.1554"}},{"value":"68628 <span class='zip-desc'>Clarks, Neb.</span>","data":{"lat":"41.2328","lon":"-97.8461"}},{"value":"68629 <span class='zip-desc'>Clarkson, Neb.</span>","data":{"lat":"41.6961","lon":"-97.1051"}},{"value":"68631 <span class='zip-desc'>Creston, Neb.</span>","data":{"lat":"41.6607","lon":"-97.3687"}},{"value":"68632 <span class='zip-desc'>David City, Neb.</span>","data":{"lat":"41.2207","lon":"-97.1572"}},{"value":"68633 <span class='zip-desc'>Dodge, Neb.</span>","data":{"lat":"41.7052","lon":"-96.8969"}},{"value":"68634 <span class='zip-desc'>Duncan, Neb.</span>","data":{"lat":"41.3931","lon":"-97.5954"}},{"value":"68635 <span class='zip-desc'>Dwight, Neb.</span>","data":{"lat":"41.0894","lon":"-96.9931"}},{"value":"68636 <span class='zip-desc'>Elgin, Neb.</span>","data":{"lat":"41.9732","lon":"-98.0751"}},{"value":"68637 <span class='zip-desc'>Ericson, Neb.</span>","data":{"lat":"41.7828","lon":"-98.6453"}},{"value":"68638 <span class='zip-desc'>Fullerton, Neb.</span>","data":{"lat":"41.366","lon":"-98.0054"}},{"value":"68640 <span class='zip-desc'>Genoa, Neb.</span>","data":{"lat":"41.4468","lon":"-97.764"}},{"value":"68641 <span class='zip-desc'>Howells, Neb.</span>","data":{"lat":"41.6964","lon":"-96.9858"}},{"value":"68642 <span class='zip-desc'>Humphrey, Neb.</span>","data":{"lat":"41.6702","lon":"-97.4986"}},{"value":"68643 <span class='zip-desc'>Leigh, Neb.</span>","data":{"lat":"41.6739","lon":"-97.232"}},{"value":"68644 <span class='zip-desc'>Lindsay, Neb.</span>","data":{"lat":"41.6926","lon":"-97.6711"}},{"value":"68647 <span class='zip-desc'>Monroe, Neb.</span>","data":{"lat":"41.4783","lon":"-97.6061"}},{"value":"68648 <span class='zip-desc'>Morse Bluff, Neb.</span>","data":{"lat":"41.4178","lon":"-96.7862"}},{"value":"68649 <span class='zip-desc'>North Bend, Neb.</span>","data":{"lat":"41.4689","lon":"-96.7813"}},{"value":"68650 <span class='zip-desc'>Octavia, Neb.</span>","data":{"lat":"41.3561","lon":"-97.0678"}},{"value":"68651 <span class='zip-desc'>Osceola, Neb.</span>","data":{"lat":"41.1966","lon":"-97.5571"}},{"value":"68652 <span class='zip-desc'>Petersburg, Neb.</span>","data":{"lat":"41.859","lon":"-98.0848"}},{"value":"68653 <span class='zip-desc'>Platte Center, Neb.</span>","data":{"lat":"41.5241","lon":"-97.4576"}},{"value":"68654 <span class='zip-desc'>Polk, Neb.</span>","data":{"lat":"41.1177","lon":"-97.7524"}},{"value":"68655 <span class='zip-desc'>Primrose, Neb.</span>","data":{"lat":"41.6405","lon":"-98.2355"}},{"value":"68658 <span class='zip-desc'>Rising City, Neb.</span>","data":{"lat":"41.2082","lon":"-97.3032"}},{"value":"68659 <span class='zip-desc'>Rogers, Neb.</span>","data":{"lat":"41.5939","lon":"-96.956"}},{"value":"68660 <span class='zip-desc'>Saint Edward, Neb.</span>","data":{"lat":"41.5708","lon":"-97.8801"}},{"value":"68661 <span class='zip-desc'>Schuyler, Neb.</span>","data":{"lat":"41.4591","lon":"-97.0628"}},{"value":"68662 <span class='zip-desc'>Shelby, Neb.</span>","data":{"lat":"41.2435","lon":"-97.4295"}},{"value":"68663 <span class='zip-desc'>Silver Creek, Neb.</span>","data":{"lat":"41.319","lon":"-97.6671"}},{"value":"68664 <span class='zip-desc'>Snyder, Neb.</span>","data":{"lat":"41.6485","lon":"-96.7873"}},{"value":"68665 <span class='zip-desc'>Spalding, Neb.</span>","data":{"lat":"41.6874","lon":"-98.3715"}},{"value":"68666 <span class='zip-desc'>Stromsburg, Neb.</span>","data":{"lat":"41.1118","lon":"-97.5742"}},{"value":"68667 <span class='zip-desc'>Surprise, Neb.</span>","data":{"lat":"41.1268","lon":"-97.2922"}},{"value":"68669 <span class='zip-desc'>Ulysses, Neb.</span>","data":{"lat":"41.0791","lon":"-97.1984"}},{"value":"68701 <span class='zip-desc'>Norfolk, Neb.</span>","data":{"lat":"42.0329","lon":"-97.4229"}},{"value":"68702 <span class='zip-desc'>Norfolk, Neb.</span>","data":{"lat":"41.9165","lon":"-97.6013"}},{"value":"68710 <span class='zip-desc'>Allen, Neb.</span>","data":{"lat":"42.4437","lon":"-96.8574"}},{"value":"68711 <span class='zip-desc'>Amelia, Neb.</span>","data":{"lat":"42.1809","lon":"-99.008"}},{"value":"68713 <span class='zip-desc'>Atkinson, Neb.</span>","data":{"lat":"42.5483","lon":"-98.9761"}},{"value":"68714 <span class='zip-desc'>Bassett, Neb.</span>","data":{"lat":"42.5763","lon":"-99.5387"}},{"value":"68715 <span class='zip-desc'>Battle Creek, Neb.</span>","data":{"lat":"41.9943","lon":"-97.5982"}},{"value":"68716 <span class='zip-desc'>Beemer, Neb.</span>","data":{"lat":"41.9374","lon":"-96.815"}},{"value":"68717 <span class='zip-desc'>Belden, Neb.</span>","data":{"lat":"42.4022","lon":"-97.1956"}},{"value":"68718 <span class='zip-desc'>Bloomfield, Neb.</span>","data":{"lat":"42.5978","lon":"-97.6545"}},{"value":"68719 <span class='zip-desc'>Bristow, Neb.</span>","data":{"lat":"42.9484","lon":"-98.5721"}},{"value":"68720 <span class='zip-desc'>Brunswick, Neb.</span>","data":{"lat":"42.3459","lon":"-98.0123"}},{"value":"68722 <span class='zip-desc'>Butte, Neb.</span>","data":{"lat":"42.9124","lon":"-98.8459"}},{"value":"68723 <span class='zip-desc'>Carroll, Neb.</span>","data":{"lat":"42.277","lon":"-97.1926"}},{"value":"68724 <span class='zip-desc'>Center, Neb.</span>","data":{"lat":"42.5973","lon":"-97.867"}},{"value":"68725 <span class='zip-desc'>Chambers, Neb.</span>","data":{"lat":"42.1916","lon":"-98.7378"}},{"value":"68726 <span class='zip-desc'>Clearwater, Neb.</span>","data":{"lat":"42.1266","lon":"-98.1868"}},{"value":"68727 <span class='zip-desc'>Coleridge, Neb.</span>","data":{"lat":"42.523","lon":"-97.1786"}},{"value":"68728 <span class='zip-desc'>Concord, Neb.</span>","data":{"lat":"42.382","lon":"-96.981"}},{"value":"68729 <span class='zip-desc'>Creighton, Neb.</span>","data":{"lat":"42.4681","lon":"-97.8932"}},{"value":"68730 <span class='zip-desc'>Crofton, Neb.</span>","data":{"lat":"42.737","lon":"-97.5406"}},{"value":"68731 <span class='zip-desc'>Dakota City, Neb.</span>","data":{"lat":"42.3807","lon":"-96.4536"}},{"value":"68732 <span class='zip-desc'>Dixon, Neb.</span>","data":{"lat":"42.4185","lon":"-96.9774"}},{"value":"68733 <span class='zip-desc'>Emerson, Neb.</span>","data":{"lat":"42.2852","lon":"-96.7159"}},{"value":"68734 <span class='zip-desc'>Emmet, Neb.</span>","data":{"lat":"42.4747","lon":"-98.8238"}},{"value":"68735 <span class='zip-desc'>Ewing, Neb.</span>","data":{"lat":"42.1851","lon":"-98.3981"}},{"value":"68736 <span class='zip-desc'>Fordyce, Neb.</span>","data":{"lat":"42.7309","lon":"-97.3567"}},{"value":"68737 <span class='zip-desc'>Foster, Neb.</span>","data":{"lat":"42.2699","lon":"-97.658"}},{"value":"68738 <span class='zip-desc'>Hadar, Neb.</span>","data":{"lat":"42.2644","lon":"-97.6013"}},{"value":"68739 <span class='zip-desc'>Hartington, Neb.</span>","data":{"lat":"42.6235","lon":"-97.2837"}},{"value":"68740 <span class='zip-desc'>Hoskins, Neb.</span>","data":{"lat":"42.1408","lon":"-97.3084"}},{"value":"68741 <span class='zip-desc'>Hubbard, Neb.</span>","data":{"lat":"42.3576","lon":"-96.6031"}},{"value":"68742 <span class='zip-desc'>Inman, Neb.</span>","data":{"lat":"42.3761","lon":"-98.5384"}},{"value":"68743 <span class='zip-desc'>Jackson, Neb.</span>","data":{"lat":"42.4529","lon":"-96.5743"}},{"value":"68745 <span class='zip-desc'>Laurel, Neb.</span>","data":{"lat":"42.427","lon":"-97.0874"}},{"value":"68746 <span class='zip-desc'>Lynch, Neb.</span>","data":{"lat":"42.8373","lon":"-98.4504"}},{"value":"68747 <span class='zip-desc'>Mclean, Neb.</span>","data":{"lat":"42.3921","lon":"-97.4751"}},{"value":"68748 <span class='zip-desc'>Madison, Neb.</span>","data":{"lat":"41.8308","lon":"-97.472"}},{"value":"68749 <span class='zip-desc'>Magnet, Neb.</span>","data":{"lat":"42.6097","lon":"-97.2504"}},{"value":"68751 <span class='zip-desc'>Maskell, Neb.</span>","data":{"lat":"42.6905","lon":"-96.9809"}},{"value":"68752 <span class='zip-desc'>Meadow Grove, Neb.</span>","data":{"lat":"42.0102","lon":"-97.7334"}},{"value":"68753 <span class='zip-desc'>Mills, Neb.</span>","data":{"lat":"42.9225","lon":"-99.4466"}},{"value":"68755 <span class='zip-desc'>Naper, Neb.</span>","data":{"lat":"42.9521","lon":"-99.071"}},{"value":"68756 <span class='zip-desc'>Neligh, Neb.</span>","data":{"lat":"42.1389","lon":"-98.0151"}},{"value":"68757 <span class='zip-desc'>Newcastle, Neb.</span>","data":{"lat":"42.6207","lon":"-96.8708"}},{"value":"68758 <span class='zip-desc'>Newman Grove, Neb.</span>","data":{"lat":"41.7498","lon":"-97.774"}},{"value":"68759 <span class='zip-desc'>Newport, Neb.</span>","data":{"lat":"42.6001","lon":"-99.3359"}},{"value":"68760 <span class='zip-desc'>Niobrara, Neb.</span>","data":{"lat":"42.7391","lon":"-97.9248"}},{"value":"68761 <span class='zip-desc'>Oakdale, Neb.</span>","data":{"lat":"42.0536","lon":"-97.9186"}},{"value":"68762 <span class='zip-desc'>Obert, Neb.</span>","data":{"lat":"42.6566","lon":"-97.0722"}},{"value":"68763 <span class='zip-desc'>Oneill, Neb.</span>","data":{"lat":"42.4857","lon":"-98.6456"}},{"value":"68764 <span class='zip-desc'>Orchard, Neb.</span>","data":{"lat":"42.3399","lon":"-98.2409"}},{"value":"68765 <span class='zip-desc'>Osmond, Neb.</span>","data":{"lat":"42.3539","lon":"-97.582"}},{"value":"68766 <span class='zip-desc'>Page, Neb.</span>","data":{"lat":"42.4119","lon":"-98.3964"}},{"value":"68767 <span class='zip-desc'>Pierce, Neb.</span>","data":{"lat":"42.1943","lon":"-97.5256"}},{"value":"68768 <span class='zip-desc'>Pilger, Neb.</span>","data":{"lat":"41.9761","lon":"-97.0779"}},{"value":"68769 <span class='zip-desc'>Plainview, Neb.</span>","data":{"lat":"42.3467","lon":"-97.7786"}},{"value":"68770 <span class='zip-desc'>Ponca, Neb.</span>","data":{"lat":"42.5693","lon":"-96.7128"}},{"value":"68771 <span class='zip-desc'>Randolph, Neb.</span>","data":{"lat":"42.3798","lon":"-97.3464"}},{"value":"68772 <span class='zip-desc'>Rose, Neb.</span>","data":{"lat":"42.4452","lon":"-99.4559"}},{"value":"68773 <span class='zip-desc'>Royal, Neb.</span>","data":{"lat":"42.3648","lon":"-98.1235"}},{"value":"68774 <span class='zip-desc'>Saint Helena, Neb.</span>","data":{"lat":"42.8046","lon":"-97.3047"}},{"value":"68776 <span class='zip-desc'>South Sioux City, Neb.</span>","data":{"lat":"42.4656","lon":"-96.4182"}},{"value":"68777 <span class='zip-desc'>Spencer, Neb.</span>","data":{"lat":"42.8849","lon":"-98.7059"}},{"value":"68778 <span class='zip-desc'>Springview, Neb.</span>","data":{"lat":"42.8488","lon":"-99.8061"}},{"value":"68779 <span class='zip-desc'>Stanton, Neb.</span>","data":{"lat":"41.9076","lon":"-97.214"}},{"value":"68780 <span class='zip-desc'>Stuart, Neb.</span>","data":{"lat":"42.5713","lon":"-99.1396"}},{"value":"68781 <span class='zip-desc'>Tilden, Neb.</span>","data":{"lat":"42.0496","lon":"-97.8223"}},{"value":"68783 <span class='zip-desc'>Verdigre, Neb.</span>","data":{"lat":"42.6101","lon":"-98.0793"}},{"value":"68784 <span class='zip-desc'>Wakefield, Neb.</span>","data":{"lat":"42.2733","lon":"-96.8776"}},{"value":"68785 <span class='zip-desc'>Waterbury, Neb.</span>","data":{"lat":"42.4604","lon":"-96.7448"}},{"value":"68786 <span class='zip-desc'>Wausa, Neb.</span>","data":{"lat":"42.4973","lon":"-97.5576"}},{"value":"68787 <span class='zip-desc'>Wayne, Neb.</span>","data":{"lat":"42.2304","lon":"-97.0186"}},{"value":"68788 <span class='zip-desc'>West Point, Neb.</span>","data":{"lat":"41.845","lon":"-96.7318"}},{"value":"68789 <span class='zip-desc'>Winnetoon, Neb.</span>","data":{"lat":"42.5334","lon":"-98.005"}},{"value":"68790 <span class='zip-desc'>Winside, Neb.</span>","data":{"lat":"42.1678","lon":"-97.1825"}},{"value":"68791 <span class='zip-desc'>Wisner, Neb.</span>","data":{"lat":"41.998","lon":"-96.917"}},{"value":"68792 <span class='zip-desc'>Wynot, Neb.</span>","data":{"lat":"42.7393","lon":"-97.1678"}},{"value":"68801 <span class='zip-desc'>Grand Island, Neb.</span>","data":{"lat":"40.9219","lon":"-98.3411"}},{"value":"68802 <span class='zip-desc'>Grand Island, Neb.</span>","data":{"lat":"40.8725","lon":"-98.5021"}},{"value":"68803 <span class='zip-desc'>Grand Island, Neb.</span>","data":{"lat":"40.9286","lon":"-98.3873"}},{"value":"68810 <span class='zip-desc'>Alda, Neb.</span>","data":{"lat":"40.8569","lon":"-98.4551"}},{"value":"68812 <span class='zip-desc'>Amherst, Neb.</span>","data":{"lat":"40.8495","lon":"-99.2609"}},{"value":"68813 <span class='zip-desc'>Anselmo, Neb.</span>","data":{"lat":"41.6208","lon":"-99.8644"}},{"value":"68814 <span class='zip-desc'>Ansley, Neb.</span>","data":{"lat":"41.3019","lon":"-99.3645"}},{"value":"68815 <span class='zip-desc'>Arcadia, Neb.</span>","data":{"lat":"41.4293","lon":"-99.1205"}},{"value":"68816 <span class='zip-desc'>Archer, Neb.</span>","data":{"lat":"41.1782","lon":"-98.1182"}},{"value":"68817 <span class='zip-desc'>Ashton, Neb.</span>","data":{"lat":"41.2672","lon":"-98.8034"}},{"value":"68818 <span class='zip-desc'>Aurora, Neb.</span>","data":{"lat":"40.8528","lon":"-98.0201"}},{"value":"68819 <span class='zip-desc'>Berwyn, Neb.</span>","data":{"lat":"41.347","lon":"-99.5016"}},{"value":"68820 <span class='zip-desc'>Boelus, Neb.</span>","data":{"lat":"41.1003","lon":"-98.6976"}},{"value":"68821 <span class='zip-desc'>Brewster, Neb.</span>","data":{"lat":"41.9467","lon":"-99.8292"}},{"value":"68822 <span class='zip-desc'>Broken Bow, Neb.</span>","data":{"lat":"41.4126","lon":"-99.6355"}},{"value":"68823 <span class='zip-desc'>Burwell, Neb.</span>","data":{"lat":"41.808","lon":"-99.0995"}},{"value":"68824 <span class='zip-desc'>Cairo, Neb.</span>","data":{"lat":"41.0002","lon":"-98.6165"}},{"value":"68825 <span class='zip-desc'>Callaway, Neb.</span>","data":{"lat":"41.2485","lon":"-99.9932"}},{"value":"68826 <span class='zip-desc'>Central City, Neb.</span>","data":{"lat":"41.1213","lon":"-98.0017"}},{"value":"68827 <span class='zip-desc'>Chapman, Neb.</span>","data":{"lat":"40.9856","lon":"-98.2217"}},{"value":"68828 <span class='zip-desc'>Comstock, Neb.</span>","data":{"lat":"41.5553","lon":"-99.2753"}},{"value":"68829 <span class='zip-desc'>Cotesfield, Neb.</span>","data":{"lat":"41.339","lon":"-98.6641"}},{"value":"68831 <span class='zip-desc'>Dannebrog, Neb.</span>","data":{"lat":"41.1192","lon":"-98.5546"}},{"value":"68832 <span class='zip-desc'>Doniphan, Neb.</span>","data":{"lat":"40.77","lon":"-98.379"}},{"value":"68833 <span class='zip-desc'>Dunning, Neb.</span>","data":{"lat":"41.8131","lon":"-100.0873"}},{"value":"68834 <span class='zip-desc'>Eddyville, Neb.</span>","data":{"lat":"41.0079","lon":"-99.681"}},{"value":"68835 <span class='zip-desc'>Elba, Neb.</span>","data":{"lat":"41.2864","lon":"-98.5756"}},{"value":"68836 <span class='zip-desc'>Elm Creek, Neb.</span>","data":{"lat":"40.7301","lon":"-99.3728"}},{"value":"68837 <span class='zip-desc'>Elyria, Neb.</span>","data":{"lat":"41.5673","lon":"-98.9816"}},{"value":"68838 <span class='zip-desc'>Farwell, Neb.</span>","data":{"lat":"41.2204","lon":"-98.6481"}},{"value":"68840 <span class='zip-desc'>Gibbon, Neb.</span>","data":{"lat":"40.7444","lon":"-98.8544"}},{"value":"68841 <span class='zip-desc'>Giltner, Neb.</span>","data":{"lat":"40.7654","lon":"-98.1434"}},{"value":"68842 <span class='zip-desc'>Greeley, Neb.</span>","data":{"lat":"41.5526","lon":"-98.53"}},{"value":"68843 <span class='zip-desc'>Hampton, Neb.</span>","data":{"lat":"40.9236","lon":"-97.8841"}},{"value":"68844 <span class='zip-desc'>Hazard, Neb.</span>","data":{"lat":"41.0934","lon":"-99.0719"}},{"value":"68845 <span class='zip-desc'>Kearney, Neb.</span>","data":{"lat":"40.7514","lon":"-99.1291"}},{"value":"68846 <span class='zip-desc'>Hordville, Neb.</span>","data":{"lat":"41.0813","lon":"-97.8881"}},{"value":"68847 <span class='zip-desc'>Kearney, Neb.</span>","data":{"lat":"40.7136","lon":"-99.0779"}},{"value":"68848 <span class='zip-desc'>Kearney, Neb.</span>","data":{"lat":"40.6861","lon":"-99.0693"}},{"value":"68849 <span class='zip-desc'>Kearney, Neb.</span>","data":{"lat":"40.8497","lon":"-99.0741"}},{"value":"68850 <span class='zip-desc'>Lexington, Neb.</span>","data":{"lat":"40.785","lon":"-99.7515"}},{"value":"68852 <span class='zip-desc'>Litchfield, Neb.</span>","data":{"lat":"41.1686","lon":"-99.1415"}},{"value":"68853 <span class='zip-desc'>Loup City, Neb.</span>","data":{"lat":"41.2845","lon":"-98.9751"}},{"value":"68854 <span class='zip-desc'>Marquette, Neb.</span>","data":{"lat":"41.01","lon":"-98"}},{"value":"68855 <span class='zip-desc'>Mason City, Neb.</span>","data":{"lat":"41.1853","lon":"-99.3049"}},{"value":"68856 <span class='zip-desc'>Merna, Neb.</span>","data":{"lat":"41.4435","lon":"-99.8036"}},{"value":"68858 <span class='zip-desc'>Miller, Neb.</span>","data":{"lat":"40.9422","lon":"-99.374"}},{"value":"68859 <span class='zip-desc'>North Loup, Neb.</span>","data":{"lat":"41.4972","lon":"-98.7858"}},{"value":"68860 <span class='zip-desc'>Oconto, Neb.</span>","data":{"lat":"41.1381","lon":"-99.6951"}},{"value":"68861 <span class='zip-desc'>Odessa, Neb.</span>","data":{"lat":"40.73","lon":"-99.2837"}},{"value":"68862 <span class='zip-desc'>Ord, Neb.</span>","data":{"lat":"41.5962","lon":"-98.9418"}},{"value":"68863 <span class='zip-desc'>Overton, Neb.</span>","data":{"lat":"40.7519","lon":"-99.5278"}},{"value":"68864 <span class='zip-desc'>Palmer, Neb.</span>","data":{"lat":"41.1788","lon":"-98.2411"}},{"value":"68865 <span class='zip-desc'>Phillips, Neb.</span>","data":{"lat":"40.8982","lon":"-98.2129"}},{"value":"68866 <span class='zip-desc'>Pleasanton, Neb.</span>","data":{"lat":"40.9818","lon":"-99.1283"}},{"value":"68868 <span class='zip-desc'>Prosser, Neb.</span>","data":{"lat":"40.6612","lon":"-98.5573"}},{"value":"68869 <span class='zip-desc'>Ravenna, Neb.</span>","data":{"lat":"41.0233","lon":"-98.9041"}},{"value":"68870 <span class='zip-desc'>Riverdale, Neb.</span>","data":{"lat":"40.8524","lon":"-99.1611"}},{"value":"68871 <span class='zip-desc'>Rockville, Neb.</span>","data":{"lat":"41.1108","lon":"-98.8578"}},{"value":"68872 <span class='zip-desc'>Saint Libory, Neb.</span>","data":{"lat":"41.0867","lon":"-98.3589"}},{"value":"68873 <span class='zip-desc'>Saint Paul, Neb.</span>","data":{"lat":"41.2242","lon":"-98.444"}},{"value":"68874 <span class='zip-desc'>Sargent, Neb.</span>","data":{"lat":"41.6508","lon":"-99.3816"}},{"value":"68875 <span class='zip-desc'>Scotia, Neb.</span>","data":{"lat":"41.4837","lon":"-98.6893"}},{"value":"68876 <span class='zip-desc'>Shelton, Neb.</span>","data":{"lat":"40.7717","lon":"-98.7435"}},{"value":"68878 <span class='zip-desc'>Sumner, Neb.</span>","data":{"lat":"40.9504","lon":"-99.52"}},{"value":"68879 <span class='zip-desc'>Taylor, Neb.</span>","data":{"lat":"41.9141","lon":"-99.4543"}},{"value":"68880 <span class='zip-desc'>Weissert, Neb.</span>","data":{"lat":"41.3939","lon":"-99.7281"}},{"value":"68881 <span class='zip-desc'>Westerville, Neb.</span>","data":{"lat":"41.4193","lon":"-99.3844"}},{"value":"68882 <span class='zip-desc'>Wolbach, Neb.</span>","data":{"lat":"41.4244","lon":"-98.3995"}},{"value":"68883 <span class='zip-desc'>Wood River, Neb.</span>","data":{"lat":"40.8106","lon":"-98.6065"}},{"value":"68901 <span class='zip-desc'>Hastings, Neb.</span>","data":{"lat":"40.5877","lon":"-98.3911"}},{"value":"68902 <span class='zip-desc'>Hastings, Neb.</span>","data":{"lat":"40.5896","lon":"-98.3972"}},{"value":"68920 <span class='zip-desc'>Alma, Neb.</span>","data":{"lat":"40.1189","lon":"-99.3601"}},{"value":"68922 <span class='zip-desc'>Arapahoe, Neb.</span>","data":{"lat":"40.3027","lon":"-99.8997"}},{"value":"68923 <span class='zip-desc'>Atlanta, Neb.</span>","data":{"lat":"40.3849","lon":"-99.4844"}},{"value":"68924 <span class='zip-desc'>Axtell, Neb.</span>","data":{"lat":"40.5269","lon":"-99.1169"}},{"value":"68925 <span class='zip-desc'>Ayr, Neb.</span>","data":{"lat":"40.4411","lon":"-98.439"}},{"value":"68926 <span class='zip-desc'>Beaver City, Neb.</span>","data":{"lat":"40.129","lon":"-99.8065"}},{"value":"68927 <span class='zip-desc'>Bertrand, Neb.</span>","data":{"lat":"40.5608","lon":"-99.5759"}},{"value":"68928 <span class='zip-desc'>Bladen, Neb.</span>","data":{"lat":"40.299","lon":"-98.6046"}},{"value":"68929 <span class='zip-desc'>Bloomington, Neb.</span>","data":{"lat":"40.1383","lon":"-99.0094"}},{"value":"68930 <span class='zip-desc'>Blue Hill, Neb.</span>","data":{"lat":"40.311","lon":"-98.427"}},{"value":"68932 <span class='zip-desc'>Campbell, Neb.</span>","data":{"lat":"40.2967","lon":"-98.737"}},{"value":"68933 <span class='zip-desc'>Clay Center, Neb.</span>","data":{"lat":"40.5113","lon":"-98.0386"}},{"value":"68934 <span class='zip-desc'>Deweese, Neb.</span>","data":{"lat":"40.354","lon":"-98.14"}},{"value":"68935 <span class='zip-desc'>Edgar, Neb.</span>","data":{"lat":"40.3652","lon":"-97.9727"}},{"value":"68936 <span class='zip-desc'>Edison, Neb.</span>","data":{"lat":"40.2802","lon":"-99.786"}},{"value":"68937 <span class='zip-desc'>Elwood, Neb.</span>","data":{"lat":"40.5747","lon":"-99.8258"}},{"value":"68938 <span class='zip-desc'>Fairfield, Neb.</span>","data":{"lat":"40.4285","lon":"-98.1063"}},{"value":"68939 <span class='zip-desc'>Franklin, Neb.</span>","data":{"lat":"40.1052","lon":"-98.9469"}},{"value":"68940 <span class='zip-desc'>Funk, Neb.</span>","data":{"lat":"40.502","lon":"-99.245"}},{"value":"68941 <span class='zip-desc'>Glenvil, Neb.</span>","data":{"lat":"40.4931","lon":"-98.2465"}},{"value":"68942 <span class='zip-desc'>Guide Rock, Neb.</span>","data":{"lat":"40.0812","lon":"-98.3391"}},{"value":"68943 <span class='zip-desc'>Hardy, Neb.</span>","data":{"lat":"40.0285","lon":"-97.9271"}},{"value":"68944 <span class='zip-desc'>Harvard, Neb.</span>","data":{"lat":"40.6265","lon":"-98.0846"}},{"value":"68945 <span class='zip-desc'>Heartwell, Neb.</span>","data":{"lat":"40.5716","lon":"-98.7851"}},{"value":"68946 <span class='zip-desc'>Hendley, Neb.</span>","data":{"lat":"40.1063","lon":"-99.9715"}},{"value":"68947 <span class='zip-desc'>Hildreth, Neb.</span>","data":{"lat":"40.3217","lon":"-99.0571"}},{"value":"68948 <span class='zip-desc'>Holbrook, Neb.</span>","data":{"lat":"40.3019","lon":"-100.0136"}},{"value":"68949 <span class='zip-desc'>Holdrege, Neb.</span>","data":{"lat":"40.4475","lon":"-99.3672"}},{"value":"68950 <span class='zip-desc'>Holstein, Neb.</span>","data":{"lat":"40.4542","lon":"-98.6538"}},{"value":"68951 <span class='zip-desc'>Huntley, Neb.</span>","data":{"lat":"40.2117","lon":"-99.2861"}},{"value":"68952 <span class='zip-desc'>Inavale, Neb.</span>","data":{"lat":"40.0959","lon":"-98.6612"}},{"value":"68954 <span class='zip-desc'>Inland, Neb.</span>","data":{"lat":"40.5899","lon":"-98.2234"}},{"value":"68955 <span class='zip-desc'>Juniata, Neb.</span>","data":{"lat":"40.5867","lon":"-98.515"}},{"value":"68956 <span class='zip-desc'>Kenesaw, Neb.</span>","data":{"lat":"40.6164","lon":"-98.6572"}},{"value":"68957 <span class='zip-desc'>Lawrence, Neb.</span>","data":{"lat":"40.2767","lon":"-98.2402"}},{"value":"68958 <span class='zip-desc'>Loomis, Neb.</span>","data":{"lat":"40.4792","lon":"-99.4979"}},{"value":"68959 <span class='zip-desc'>Minden, Neb.</span>","data":{"lat":"40.5091","lon":"-98.9383"}},{"value":"68960 <span class='zip-desc'>Naponee, Neb.</span>","data":{"lat":"40.1258","lon":"-99.1277"}},{"value":"68961 <span class='zip-desc'>Nelson, Neb.</span>","data":{"lat":"40.201","lon":"-98.0684"}},{"value":"68963 <span class='zip-desc'>Norman, Neb.</span>","data":{"lat":"40.4789","lon":"-98.7927"}},{"value":"68964 <span class='zip-desc'>Oak, Neb.</span>","data":{"lat":"40.2378","lon":"-97.903"}},{"value":"68966 <span class='zip-desc'>Orleans, Neb.</span>","data":{"lat":"40.1484","lon":"-99.4572"}},{"value":"68967 <span class='zip-desc'>Oxford, Neb.</span>","data":{"lat":"40.256","lon":"-99.6302"}},{"value":"68969 <span class='zip-desc'>Ragan, Neb.</span>","data":{"lat":"40.1765","lon":"-99.4049"}},{"value":"68970 <span class='zip-desc'>Red Cloud, Neb.</span>","data":{"lat":"40.0952","lon":"-98.5187"}},{"value":"68971 <span class='zip-desc'>Republican City, Neb.</span>","data":{"lat":"40.1034","lon":"-99.2322"}},{"value":"68972 <span class='zip-desc'>Riverton, Neb.</span>","data":{"lat":"40.1016","lon":"-98.7858"}},{"value":"68973 <span class='zip-desc'>Roseland, Neb.</span>","data":{"lat":"40.4591","lon":"-98.5551"}},{"value":"68974 <span class='zip-desc'>Ruskin, Neb.</span>","data":{"lat":"40.1383","lon":"-97.872"}},{"value":"68975 <span class='zip-desc'>Saronville, Neb.</span>","data":{"lat":"40.6021","lon":"-97.9388"}},{"value":"68976 <span class='zip-desc'>Smithfield, Neb.</span>","data":{"lat":"40.5832","lon":"-99.7285"}},{"value":"68977 <span class='zip-desc'>Stamford, Neb.</span>","data":{"lat":"40.1162","lon":"-99.5814"}},{"value":"68978 <span class='zip-desc'>Superior, Neb.</span>","data":{"lat":"40.0315","lon":"-98.0779"}},{"value":"68979 <span class='zip-desc'>Sutton, Neb.</span>","data":{"lat":"40.654","lon":"-97.8735"}},{"value":"68980 <span class='zip-desc'>Trumbull, Neb.</span>","data":{"lat":"40.6692","lon":"-98.2574"}},{"value":"68981 <span class='zip-desc'>Upland, Neb.</span>","data":{"lat":"40.3171","lon":"-98.8966"}},{"value":"68982 <span class='zip-desc'>Wilcox, Neb.</span>","data":{"lat":"40.3735","lon":"-99.1539"}}]}
