{"suggestions":[{"value":"Fairfield, Calif.","data":{"lat":"38.24936","lon":"-122.03997"}},{"value":"Fargo, N.D.","data":{"lat":"46.87719","lon":"-96.7898"}},{"value":"Fayetteville, N.C.","data":{"lat":"35.05266","lon":"-78.87836"}},{"value":"Fair Lawn, N.J.","data":{"lat":"40.94038","lon":"-74.13181"}},{"value":"Fair Oaks, Calif.","data":{"lat":"38.64463","lon":"-121.27217"}},{"value":"Fairbanks, Alaska","data":{"lat":"64.83778","lon":"-147.71639"}},{"value":"Fairborn, Ohio","data":{"lat":"39.82089","lon":"-84.01938"}},{"value":"Fairburn, Ga.","data":{"lat":"33.56706","lon":"-84.58104"}},{"value":"Fairfax, Va.","data":{"lat":"38.84622","lon":"-77.30637"}},{"value":"Fairfax Station, Va.","data":{"lat":"38.80095","lon":"-77.32554"}},{"value":"Fairfield, Ala.","data":{"lat":"33.48594","lon":"-86.91194"}},{"value":"Fairfield, Ohio","data":{"lat":"39.34589","lon":"-84.5605"}},{"value":"Fairfield, Conn.","data":{"lat":"41.14121","lon":"-73.26373"}},{"value":"Fairfield Heights, Ind.","data":{"lat":"39.82861","lon":"-86.38224"}},{"value":"Fairhaven, Mass.","data":{"lat":"41.6376","lon":"-70.90365"}},{"value":"Fairhope, Ala.","data":{"lat":"30.52297","lon":"-87.90333"}},{"value":"Fairland, Md.","data":{"lat":"39.07622","lon":"-76.95775"}},{"value":"Fairmont, Minn.","data":{"lat":"43.65218","lon":"-94.46108"}},{"value":"Fairmont, W.V.","data":{"lat":"39.48508","lon":"-80.14258"}},{"value":"Fairmount, N.Y.","data":{"lat":"43.04729","lon":"-76.23854"}},{"value":"Fairview, N.J.","data":{"lat":"40.8126","lon":"-73.99903"}},{"value":"Fairview, Calif.","data":{"lat":"37.67854","lon":"-122.0458"}},{"value":"Fairview Heights, Ill.","data":{"lat":"38.58894","lon":"-89.99038"}},{"value":"Fairview Park, Ohio","data":{"lat":"41.44144","lon":"-81.8643"}},{"value":"Fairview Shores, Fla.","data":{"lat":"28.59111","lon":"-81.39424"}},{"value":"Fairwood, Wash.","data":{"lat":"47.44843","lon":"-122.15734"}},{"value":"Fall River, Mass.","data":{"lat":"41.70149","lon":"-71.15505"}},{"value":"Fallbrook, Calif.","data":{"lat":"33.37642","lon":"-117.25115"}},{"value":"Falls Church, Va.","data":{"lat":"38.88233","lon":"-77.17109"}},{"value":"Faribault, Minn.","data":{"lat":"44.29496","lon":"-93.26883"}},{"value":"Farmers Branch, Tex.","data":{"lat":"32.92651","lon":"-96.89612"}},{"value":"Farmersville, Calif.","data":{"lat":"36.29773","lon":"-119.20678"}},{"value":"Farmington, Minn.","data":{"lat":"44.64024","lon":"-93.14355"}},{"value":"Farmington, Mo.","data":{"lat":"37.78088","lon":"-90.42179"}},{"value":"Farmington, Mich.","data":{"lat":"42.46448","lon":"-83.37632"}},{"value":"Farmington, Utah","data":{"lat":"40.9805","lon":"-111.88744"}},{"value":"Farmington, Conn.","data":{"lat":"41.71982","lon":"-72.83204"}},{"value":"Farmington, N.M.","data":{"lat":"36.72806","lon":"-108.21869"}},{"value":"Farmington Hills, Mich.","data":{"lat":"42.48531","lon":"-83.37716"}},{"value":"Farmingville, N.Y.","data":{"lat":"40.83121","lon":"-73.02955"}},{"value":"Farragut, Tenn.","data":{"lat":"35.88452","lon":"-84.15353"}},{"value":"Fayetteville, Ark.","data":{"lat":"36.06258","lon":"-94.15743"}},{"value":"Fayetteville, Ga.","data":{"lat":"33.44873","lon":"-84.45493"}},{"value":"Fabens, Tex.","data":{"lat":"31.50234","lon":"-106.15859"}},{"value":"Factoryville, Pa.","data":{"lat":"41.56313","lon":"-75.78269"}},{"value":"Factoryville, Pa.","data":{"lat":"40.82482","lon":"-75.20962"}},{"value":"Fair Grove, Mo.","data":{"lat":"37.38393","lon":"-93.1513"}},{"value":"Fair Haven, Vt.","data":{"lat":"43.59479","lon":"-73.26567"}},{"value":"Fair Haven, N.J.","data":{"lat":"40.36067","lon":"-74.03819"}},{"value":"Fair Oaks, Ga.","data":{"lat":"33.91649","lon":"-84.54465"}},{"value":"Fair Oaks Ranch, Tex.","data":{"lat":"29.74578","lon":"-98.64336"}},{"value":"Fair Plain, Mich.","data":{"lat":"42.08699","lon":"-86.45586"}},{"value":"Fairbank, Iowa","data":{"lat":"42.63915","lon":"-92.04712"}},{"value":"Fairbanks Ranch, Calif.","data":{"lat":"32.99393","lon":"-117.18726"}},{"value":"Fairbury, Neb.","data":{"lat":"40.13722","lon":"-97.18059"}},{"value":"Fairbury, Ill.","data":{"lat":"40.74726","lon":"-88.51478"}},{"value":"Fairchance, Pa.","data":{"lat":"39.8248","lon":"-79.75449"}},{"value":"Fairchild Air Force Base, Wash.","data":{"lat":"47.61879","lon":"-117.64826"}},{"value":"Fairdale, Pa.","data":{"lat":"39.88702","lon":"-79.96811"}},{"value":"Fairdale, Ky.","data":{"lat":"38.10507","lon":"-85.75885"}},{"value":"Fairfax, Iowa","data":{"lat":"41.91945","lon":"-91.78101"}},{"value":"Fairfax, Okla.","data":{"lat":"36.57366","lon":"-96.7042"}},{"value":"Fairfax, Calif.","data":{"lat":"37.98715","lon":"-122.58887"}},{"value":"Fairfax, S.C.","data":{"lat":"32.95905","lon":"-81.2365"}},{"value":"Fairfax, Minn.","data":{"lat":"44.52913","lon":"-94.72082"}},{"value":"Fairfax, Ohio","data":{"lat":"39.14534","lon":"-84.39327"}},{"value":"Fairfield, Ill.","data":{"lat":"42.21919","lon":"-88.06147"}},{"value":"Fairfield, Maine","data":{"lat":"44.5884","lon":"-69.59866"}},{"value":"Fairfield, Tex.","data":{"lat":"31.72461","lon":"-96.16525"}},{"value":"Fairfield, N.J.","data":{"lat":"40.88371","lon":"-74.30598"}},{"value":"Fairfield, Iowa","data":{"lat":"41.00863","lon":"-91.96267"}},{"value":"Fairfield, Ill.","data":{"lat":"38.37894","lon":"-88.35977"}},{"value":"Fairfield Bay, Ark.","data":{"lat":"35.59424","lon":"-92.27793"}},{"value":"Fairfield Beach, Ohio","data":{"lat":"39.9159","lon":"-82.47516"}},{"value":"Fairfield Glade, Tenn.","data":{"lat":"36.00035","lon":"-84.88634"}},{"value":"Fairfield Harbour, N.C.","data":{"lat":"35.07655","lon":"-76.96356"}},{"value":"Fairforest, S.C.","data":{"lat":"34.95651","lon":"-82.01011"}},{"value":"Fairhope, Pa.","data":{"lat":"40.11368","lon":"-79.83977"}},{"value":"Fairland, Okla.","data":{"lat":"36.75118","lon":"-94.84746"}},{"value":"Fairlawn, Va.","data":{"lat":"37.77624","lon":"-79.982"}},{"value":"Fairlawn, Va.","data":{"lat":"37.14846","lon":"-80.57839"}},{"value":"Fairlawn, Ohio","data":{"lat":"41.12783","lon":"-81.60984"}},{"value":"Fairlea, W.V.","data":{"lat":"37.78068","lon":"-80.45702"}},{"value":"Fairless Hills, Pa.","data":{"lat":"40.17955","lon":"-74.85516"}},{"value":"Fairmead, Calif.","data":{"lat":"37.07633","lon":"-120.19295"}},{"value":"Fairmont, Ill.","data":{"lat":"41.55614","lon":"-88.05923"}},{"value":"Fairmont, N.C.","data":{"lat":"34.49683","lon":"-79.1142"}},{"value":"Fairmont City, Ill.","data":{"lat":"38.64977","lon":"-90.09316"}},{"value":"Fairmount, Tenn.","data":{"lat":"36.58511","lon":"-82.17097"}},{"value":"Fairmount, Tenn.","data":{"lat":"35.18146","lon":"-85.32357"}},{"value":"Fairmount, Ind.","data":{"lat":"40.41532","lon":"-85.65053"}},{"value":"Fairmount Heights, Md.","data":{"lat":"38.90095","lon":"-76.91553"}},{"value":"Fairplains, N.C.","data":{"lat":"36.19847","lon":"-81.15286"}},{"value":"Fairport, N.Y.","data":{"lat":"43.09867","lon":"-77.44194"}},{"value":"Fairport Harbor, Ohio","data":{"lat":"41.75004","lon":"-81.27399"}},{"value":"Fairton, N.J.","data":{"lat":"39.38178","lon":"-75.21991"}},{"value":"Fairview, Pa.","data":{"lat":"42.03145","lon":"-80.25534"}},{"value":"Fairview, N.C.","data":{"lat":"35.51401","lon":"-82.39595"}},{"value":"Fairview, N.J.","data":{"lat":"40.37316","lon":"-74.08681"}},{"value":"Fairview, Utah","data":{"lat":"39.62635","lon":"-111.43963"}},{"value":"Fairview, Ore.","data":{"lat":"45.53845","lon":"-122.43398"}},{"value":"Fairview, Ga.","data":{"lat":"34.94563","lon":"-85.2844"}},{"value":"Fairview, Tex.","data":{"lat":"33.01929","lon":"-97.54586"}},{"value":"Fairview, N.C.","data":{"lat":"35.13848","lon":"-80.53757"}},{"value":"Fairview, N.Y.","data":{"lat":"41.7237","lon":"-73.91986"}},{"value":"Fairview, Tex.","data":{"lat":"33.1579","lon":"-96.63166"}},{"value":"Fairview, Okla.","data":{"lat":"36.26892","lon":"-98.4798"}},{"value":"Fairview, Tenn.","data":{"lat":"35.98201","lon":"-87.1214"}},{"value":"Fairview, N.Y.","data":{"lat":"41.04343","lon":"-73.79736"}},{"value":"Fairview Park, Ind.","data":{"lat":"39.68031","lon":"-87.41752"}},{"value":"Fairview-Ferndale, Pa.","data":{"lat":"40.78037","lon":"-76.57528"}},{"value":"Fairway, Kan.","data":{"lat":"39.02223","lon":"-94.6319"}},{"value":"Fairwood, Wash.","data":{"lat":"47.76684","lon":"-117.41744"}},{"value":"Falcon Heights, Minn.","data":{"lat":"44.99163","lon":"-93.16633"}},{"value":"Falcon Lake Estates, Tex.","data":{"lat":"26.87282","lon":"-99.25531"}},{"value":"Falconer, N.Y.","data":{"lat":"42.11867","lon":"-79.19838"}},{"value":"Falfurrias, Tex.","data":{"lat":"27.22699","lon":"-98.14417"}},{"value":"Falkville, Ala.","data":{"lat":"34.36843","lon":"-86.90862"}},{"value":"Fall Branch, Tenn.","data":{"lat":"36.41816","lon":"-82.62376"}},{"value":"Fall City, Wash.","data":{"lat":"47.56732","lon":"-121.88873"}},{"value":"Fall Creek, Wis.","data":{"lat":"44.76357","lon":"-91.2771"}},{"value":"Fall River, Wis.","data":{"lat":"43.38443","lon":"-89.04511"}},{"value":"Falling Water, Tenn.","data":{"lat":"35.20312","lon":"-85.25357"}},{"value":"Fallon, Nev.","data":{"lat":"39.47353","lon":"-118.77737"}},{"value":"Falls City, Neb.","data":{"lat":"40.06084","lon":"-95.60193"}},{"value":"Falls Creek, Pa.","data":{"lat":"41.14506","lon":"-78.80447"}},{"value":"Fallston, Md.","data":{"lat":"39.51455","lon":"-76.41107"}},{"value":"Falmouth, Ky.","data":{"lat":"38.67674","lon":"-84.33021"}},{"value":"Falmouth, Mass.","data":{"lat":"41.5515","lon":"-70.61475"}},{"value":"Falmouth, Va.","data":{"lat":"38.32402","lon":"-77.46832"}},{"value":"Falmouth, Maine","data":{"lat":"43.72952","lon":"-70.24199"}},{"value":"Falmouth Foreside, Maine","data":{"lat":"43.7348","lon":"-70.20783"}},{"value":"Fannett, Tex.","data":{"lat":"29.92605","lon":"-94.25074"}},{"value":"Fanwood, N.J.","data":{"lat":"40.64094","lon":"-74.38348"}},{"value":"Farley, Iowa","data":{"lat":"42.44278","lon":"-91.00625"}},{"value":"Farm Loop, Alaska","data":{"lat":"61.63891","lon":"-149.14215"}},{"value":"Farmer City, Ill.","data":{"lat":"40.24337","lon":"-88.64257"}},{"value":"Farmersburg, Ind.","data":{"lat":"39.24865","lon":"-87.38196"}},{"value":"Farmersville, Ohio","data":{"lat":"39.6795","lon":"-84.42911"}},{"value":"Farmersville, Tex.","data":{"lat":"33.16345","lon":"-96.35998"}},{"value":"Farmerville, La.","data":{"lat":"32.77347","lon":"-92.4057"}},{"value":"Farmingdale, N.J.","data":{"lat":"40.1965","lon":"-74.16848"}},{"value":"Farmingdale, N.Y.","data":{"lat":"40.7326","lon":"-73.4454"}},{"value":"Farmingdale, Maine","data":{"lat":"44.24451","lon":"-69.77143"}},{"value":"Farmington, Ill.","data":{"lat":"40.69809","lon":"-90.00595"}},{"value":"Farmington, Maine","data":{"lat":"44.67062","lon":"-70.15117"}},{"value":"Farmington, Ark.","data":{"lat":"36.04202","lon":"-94.24715"}},{"value":"Farmington, Miss.","data":{"lat":"34.93009","lon":"-88.45227"}},{"value":"Farmington, N.H.","data":{"lat":"43.3898","lon":"-71.06506"}},{"value":"Farmington, Ill.","data":{"lat":"41.94475","lon":"-88.31591"}},{"value":"Farmland, Ind.","data":{"lat":"40.18782","lon":"-85.12747"}},{"value":"Farmville, N.C.","data":{"lat":"35.59544","lon":"-77.58525"}},{"value":"Farmville, N.C.","data":{"lat":"35.57071","lon":"-79.22002"}},{"value":"Farmville, Va.","data":{"lat":"37.3021","lon":"-78.39194"}},{"value":"Farr West, Utah","data":{"lat":"41.29717","lon":"-112.02772"}},{"value":"Farrell, Pa.","data":{"lat":"41.21228","lon":"-80.49674"}},{"value":"Farwell, Tex.","data":{"lat":"34.38341","lon":"-103.038"}},{"value":"Fate, Tex.","data":{"lat":"32.94151","lon":"-96.38137"}},{"value":"Faxon, Pa.","data":{"lat":"41.24841","lon":"-76.97719"}},{"value":"Fayette, Ala.","data":{"lat":"33.68455","lon":"-87.83085"}},{"value":"Fayette, Maine","data":{"lat":"44.40896","lon":"-70.03367"}},{"value":"Fayette, Ohio","data":{"lat":"41.67338","lon":"-84.32689"}},{"value":"Fayette, Iowa","data":{"lat":"42.84193","lon":"-91.80211"}},{"value":"Fayette, Miss.","data":{"lat":"31.71155","lon":"-91.06066"}},{"value":"Fayette, Mo.","data":{"lat":"39.14587","lon":"-92.68379"}},{"value":"Fayetteville, Ala.","data":{"lat":"33.14567","lon":"-86.40581"}},{"value":"Fayetteville, Pa.","data":{"lat":"39.9112","lon":"-77.54999"}},{"value":"Fayetteville, N.Y.","data":{"lat":"43.02979","lon":"-76.00436"}},{"value":"Fayetteville, Tenn.","data":{"lat":"35.15203","lon":"-86.57055"}},{"value":"Fayetteville, W.V.","data":{"lat":"38.05289","lon":"-81.10399"}},{"value":"Fabius, N.Y.","data":{"lat":"42.83507","lon":"-75.98603"}},{"value":"Fair Bluff, N.C.","data":{"lat":"34.3135","lon":"-79.03725"}},{"value":"Fair Garden, Tenn.","data":{"lat":"35.90231","lon":"-83.41294"}},{"value":"Fair Haven, N.Y.","data":{"lat":"42.76923","lon":"-76.26826"}},{"value":"Fair Haven, N.Y.","data":{"lat":"43.31646","lon":"-76.70217"}},{"value":"Fair Oaks, Okla.","data":{"lat":"36.14815","lon":"-95.70859"}},{"value":"Fair Oaks, Ore.","data":{"lat":"43.41734","lon":"-123.21341"}},{"value":"Fair Play, Mo.","data":{"lat":"37.63004","lon":"-93.57326"}},{"value":"Fair Play, S.C.","data":{"lat":"34.51121","lon":"-82.98543"}},{"value":"Fairacres, N.M.","data":{"lat":"32.30398","lon":"-106.84667"}},{"value":"Fairchild, Wis.","data":{"lat":"44.60024","lon":"-90.96293"}},{"value":"Fairchilds, Tex.","data":{"lat":"29.43135","lon":"-95.78023"}},{"value":"Fairdealing, Mo.","data":{"lat":"36.66283","lon":"-90.61678"}},{"value":"Fairfax, Mo.","data":{"lat":"40.33861","lon":"-95.39331"}},{"value":"Fairfax, S.D.","data":{"lat":"43.0275","lon":"-98.88842"}},{"value":"Fairfield, Idaho","data":{"lat":"43.34657","lon":"-114.79173"}},{"value":"Fairfield, Mont.","data":{"lat":"47.61467","lon":"-111.98028"}},{"value":"Fairfield, Pa.","data":{"lat":"40.01341","lon":"-80.07117"}},{"value":"Fairfield, Tenn.","data":{"lat":"36.61976","lon":"-86.34555"}},{"value":"Fairfield, Neb.","data":{"lat":"40.43168","lon":"-98.10588"}},{"value":"Fairfield, Pa.","data":{"lat":"39.78732","lon":"-77.3686"}},{"value":"Fairfield, Wash.","data":{"lat":"47.38518","lon":"-117.17158"}},{"value":"Fairfield, N.C.","data":{"lat":"35.54128","lon":"-76.22436"}},{"value":"Fairfield, Ky.","data":{"lat":"37.93367","lon":"-85.38357"}},{"value":"Fairfield, Okla.","data":{"lat":"35.84731","lon":"-94.61244"}},{"value":"Fairfield, Utah","data":{"lat":"40.26217","lon":"-112.093"}},{"value":"Fairford, Ala.","data":{"lat":"31.16823","lon":"-88.06417"}},{"value":"Fairgrove, Mich.","data":{"lat":"43.52363","lon":"-83.54329"}},{"value":"Fairhaven, Minn.","data":{"lat":"45.32163","lon":"-94.21138"}},{"value":"Fairland, Ind.","data":{"lat":"39.58588","lon":"-85.86359"}},{"value":"Fairlee, Md.","data":{"lat":"39.22261","lon":"-76.1719"}},{"value":"Fairlee, Vt.","data":{"lat":"43.90757","lon":"-72.14342"}},{"value":"Fairmeade, Ky.","data":{"lat":"38.24896","lon":"-85.63385"}},{"value":"Fairmont, Neb.","data":{"lat":"40.63695","lon":"-97.58533"}},{"value":"Fairmont, Okla.","data":{"lat":"36.35559","lon":"-97.70561"}},{"value":"Fairmount, Ill.","data":{"lat":"40.04559","lon":"-87.83058"}},{"value":"Fairmount, Ga.","data":{"lat":"34.4362","lon":"-84.69993"}},{"value":"Fairmount, Md.","data":{"lat":"38.0904","lon":"-75.81743"}},{"value":"Fairmount, N.D.","data":{"lat":"46.05496","lon":"-96.60229"}},{"value":"Fairplay, Colo.","data":{"lat":"39.22471","lon":"-106.00196"}},{"value":"Fairplay, Md.","data":{"lat":"39.53649","lon":"-77.74749"}},{"value":"Fairview, Ala.","data":{"lat":"34.25537","lon":"-86.68805"}},{"value":"Fairview, Ill.","data":{"lat":"40.63337","lon":"-90.16373"}},{"value":"Fairview, Kan.","data":{"lat":"39.84111","lon":"-95.72804"}},{"value":"Fairview, Wyo.","data":{"lat":"42.68854","lon":"-110.98243"}},{"value":"Fairview, Mo.","data":{"lat":"36.81757","lon":"-94.08827"}},{"value":"Fairview, Pa.","data":{"lat":"41.01451","lon":"-79.74283"}},{"value":"Fairview, W.V.","data":{"lat":"39.59258","lon":"-80.24758"}},{"value":"Fairview, Mont.","data":{"lat":"47.85641","lon":"-104.04493"}},{"value":"Fairview, Ky.","data":{"lat":"36.84338","lon":"-87.30389"}},{"value":"Fairview, Va.","data":{"lat":"36.81542","lon":"-78.46666"}},{"value":"Fairview, Ky.","data":{"lat":"38.99839","lon":"-84.48716"}},{"value":"Fairview Beach, Va.","data":{"lat":"38.33013","lon":"-77.2472"}},{"value":"Fairwater, Wis.","data":{"lat":"43.74387","lon":"-88.86706"}},{"value":"Faison, N.C.","data":{"lat":"35.11628","lon":"-78.1361"}},{"value":"Faith, S.D.","data":{"lat":"45.02304","lon":"-102.03599"}},{"value":"Faith, N.C.","data":{"lat":"35.58708","lon":"-80.46284"}},{"value":"Falcon, Miss.","data":{"lat":"34.39316","lon":"-90.25648"}},{"value":"Falcon, N.C.","data":{"lat":"35.18989","lon":"-78.64835"}},{"value":"Falcon Mesa, Tex.","data":{"lat":"26.87282","lon":"-99.28948"}},{"value":"Falkner, Miss.","data":{"lat":"34.84204","lon":"-88.93423"}},{"value":"Fall River, Kan.","data":{"lat":"37.60782","lon":"-96.02804"}},{"value":"Fall River Mills, Calif.","data":{"lat":"41.00461","lon":"-121.43831"}},{"value":"Falling Spring, W.V.","data":{"lat":"37.99179","lon":"-80.35396"}},{"value":"Falling Waters, W.V.","data":{"lat":"39.55926","lon":"-77.89083"}},{"value":"Fallon, Mont.","data":{"lat":"46.83556","lon":"-105.11942"}},{"value":"Fallon Station, Nev.","data":{"lat":"39.41596","lon":"-118.71653"}},{"value":"Falls City, Tex.","data":{"lat":"28.98275","lon":"-98.0175"}},{"value":"Falls City, Ore.","data":{"lat":"44.86623","lon":"-123.43594"}},{"value":"Falls View, W.V.","data":{"lat":"38.12622","lon":"-81.24622"}},{"value":"Falls Village, Conn.","data":{"lat":"41.95593","lon":"-73.36317"}},{"value":"Fallston, Pa.","data":{"lat":"40.72562","lon":"-80.31562"}},{"value":"Fallston, N.C.","data":{"lat":"35.42902","lon":"-81.50148"}},{"value":"Falmouth, Pa.","data":{"lat":"40.12954","lon":"-76.71386"}},{"value":"Fancy Farm, Ky.","data":{"lat":"36.7995","lon":"-88.79144"}},{"value":"Fancy Gap, Va.","data":{"lat":"36.66596","lon":"-80.69229"}},{"value":"Fanning Springs, Fla.","data":{"lat":"29.59079","lon":"-82.92929"}},{"value":"Fanshawe, Okla.","data":{"lat":"34.95093","lon":"-94.90829"}},{"value":"Far Hills, N.J.","data":{"lat":"40.68427","lon":"-74.63571"}},{"value":"Farber, Mo.","data":{"lat":"39.27254","lon":"-91.5746"}},{"value":"Fargo, Okla.","data":{"lat":"36.37615","lon":"-99.62373"}},{"value":"Fargo, Ga.","data":{"lat":"30.68188","lon":"-82.56652"}},{"value":"Farina, Ill.","data":{"lat":"38.83421","lon":"-88.77228"}},{"value":"Farley, Mo.","data":{"lat":"39.28222","lon":"-94.83135"}},{"value":"Farmers, Ky.","data":{"lat":"38.14286","lon":"-83.54602"}},{"value":"Farmersburg, Iowa","data":{"lat":"42.9611","lon":"-91.36791"}},{"value":"Farmersville, Ill.","data":{"lat":"39.44339","lon":"-89.65176"}},{"value":"Farmersville, Pa.","data":{"lat":"40.1276","lon":"-76.16495"}},{"value":"Farmington, Pa.","data":{"lat":"39.8073","lon":"-79.5656"}},{"value":"Farmington, Ky.","data":{"lat":"36.6695","lon":"-88.52588"}},{"value":"Farmington, Del.","data":{"lat":"38.86928","lon":"-75.57854"}},{"value":"Farmington, Calif.","data":{"lat":"37.92992","lon":"-121.00022"}},{"value":"Farmington, W.V.","data":{"lat":"39.51286","lon":"-80.24897"}},{"value":"Farmington, Wash.","data":{"lat":"47.08934","lon":"-117.04406"}},{"value":"Farmington, Iowa","data":{"lat":"40.64031","lon":"-91.74294"}},{"value":"Farnam, Neb.","data":{"lat":"40.70584","lon":"-100.21486"}},{"value":"Farnham, N.Y.","data":{"lat":"42.5945","lon":"-79.09115"}},{"value":"Farnhamville, Iowa","data":{"lat":"42.27609","lon":"-94.40386"}},{"value":"Farragut, Iowa","data":{"lat":"40.72194","lon":"-95.48082"}},{"value":"Farrell, Miss.","data":{"lat":"34.26427","lon":"-90.67232"}},{"value":"Farson, Wyo.","data":{"lat":"42.11051","lon":"-109.44096"}},{"value":"Farwell, Mich.","data":{"lat":"43.83502","lon":"-84.86697"}},{"value":"Farwell, Neb.","data":{"lat":"41.21557","lon":"-98.62813"}},{"value":"Faulkton, S.D.","data":{"lat":"45.03497","lon":"-99.124"}},{"value":"Fawn Grove, Pa.","data":{"lat":"39.72788","lon":"-76.45191"}},{"value":"Fawn Lake Forest, Pa.","data":{"lat":"41.50842","lon":"-75.06434"}},{"value":"Faxon, Okla.","data":{"lat":"34.45702","lon":"-98.57895"}},{"value":"Fayette, Utah","data":{"lat":"39.22524","lon":"-111.85659"}},{"value":"Fayette City, Pa.","data":{"lat":"40.10035","lon":"-79.8406"}},{"value":"Fayetteville, Ill.","data":{"lat":"38.37755","lon":"-89.79538"}},{"value":"Fayetteville, Ohio","data":{"lat":"39.18673","lon":"-83.93215"}},{"value":"Fayetteville, Tex.","data":{"lat":"29.90578","lon":"-96.67275"}},{"value":"Faysville, Tex.","data":{"lat":"26.41035","lon":"-98.13529"}},{"value":"Fairburn, S.D.","data":{"lat":"43.6861","lon":"-103.21158"}},{"value":"Fairdale, N.D.","data":{"lat":"48.49083","lon":"-98.23122"}},{"value":"Fairview, S.D.","data":{"lat":"43.22165","lon":"-96.49004"}},{"value":"Fairview, Md.","data":{"lat":"39.71232","lon":"-77.84305"}},{"value":"Fairview, Ohio","data":{"lat":"40.05701","lon":"-81.23289"}},{"value":"Fairview, Md.","data":{"lat":"39.7037","lon":"-78.17778"}},{"value":"Falcon Heights, Tex.","data":{"lat":"26.55894","lon":"-99.12309"}},{"value":"Falcon Village, Tex.","data":{"lat":"26.56144","lon":"-99.13448"}},{"value":"Falkland, N.C.","data":{"lat":"35.69933","lon":"-77.51303"}},{"value":"Fallis, Okla.","data":{"lat":"35.74839","lon":"-97.12059"}},{"value":"False Pass, Alaska","data":{"lat":"54.85083","lon":"-163.415"}},{"value":"Falun, Kan.","data":{"lat":"38.67112","lon":"-97.75949"}},{"value":"Fargo, Ark.","data":{"lat":"34.95148","lon":"-91.18012"}},{"value":"Farwell, Minn.","data":{"lat":"45.75218","lon":"-95.61727"}},{"value":"Faunsdale, Ala.","data":{"lat":"32.45986","lon":"-87.59389"}},{"value":"Farmer, S.D.","data":{"lat":"43.72387","lon":"-97.6884"}}]}
