{"suggestions":[{"value":"Hampton, Va.","data":{"lat":"37.02987","lon":"-76.34522"}},{"value":"Hartford, Conn.","data":{"lat":"41.76371","lon":"-72.68509"}},{"value":"Hayward, Calif.","data":{"lat":"37.66882","lon":"-122.0808"}},{"value":"Hacienda Heights, Calif.","data":{"lat":"33.99307","lon":"-117.96868"}},{"value":"Hackensack, N.J.","data":{"lat":"40.88593","lon":"-74.04347"}},{"value":"Haddonfield, N.J.","data":{"lat":"39.8915","lon":"-75.03767"}},{"value":"Hagerstown, Md.","data":{"lat":"39.64176","lon":"-77.71999"}},{"value":"Haines City, Fla.","data":{"lat":"28.11418","lon":"-81.61785"}},{"value":"Halawa, Hawaii","data":{"lat":"21.37944","lon":"-157.92167"}},{"value":"Halawa Heights, Hawaii","data":{"lat":"21.37848","lon":"-157.91388"}},{"value":"Half Moon Bay, Calif.","data":{"lat":"37.46355","lon":"-122.42859"}},{"value":"Halfway, Md.","data":{"lat":"39.62065","lon":"-77.75888"}},{"value":"Hallandale Beach, Fla.","data":{"lat":"25.9812","lon":"-80.14838"}},{"value":"Haltom City, Tex.","data":{"lat":"32.79957","lon":"-97.26918"}},{"value":"Ham Lake, Minn.","data":{"lat":"45.25024","lon":"-93.24995"}},{"value":"Hamden, Conn.","data":{"lat":"41.39593","lon":"-72.89677"}},{"value":"Hamilton, Ohio","data":{"lat":"39.3995","lon":"-84.56134"}},{"value":"Hamilton Square, N.J.","data":{"lat":"40.22733","lon":"-74.65321"}},{"value":"Hammond, La.","data":{"lat":"30.50436","lon":"-90.4612"}},{"value":"Hammond, Ind.","data":{"lat":"41.58337","lon":"-87.50004"}},{"value":"Hammonton, N.J.","data":{"lat":"39.63651","lon":"-74.80239"}},{"value":"Hampton Bays, N.Y.","data":{"lat":"40.86899","lon":"-72.51759"}},{"value":"Hamtramck, Mich.","data":{"lat":"42.39282","lon":"-83.04964"}},{"value":"Hanahan, S.C.","data":{"lat":"32.91851","lon":"-80.02203"}},{"value":"Hanford, Calif.","data":{"lat":"36.32745","lon":"-119.64568"}},{"value":"Hannibal, Mo.","data":{"lat":"39.70838","lon":"-91.35848"}},{"value":"Hanover, Md.","data":{"lat":"39.19289","lon":"-76.72414"}},{"value":"Hanover, Mass.","data":{"lat":"42.11316","lon":"-70.81199"}},{"value":"Hanover, N.J.","data":{"lat":"40.80454","lon":"-74.36682"}},{"value":"Hanover, Pa.","data":{"lat":"39.80066","lon":"-76.98304"}},{"value":"Hanover Park, Ill.","data":{"lat":"41.99947","lon":"-88.14507"}},{"value":"Happy Valley, Ore.","data":{"lat":"45.44679","lon":"-122.53037"}},{"value":"Harker Heights, Tex.","data":{"lat":"31.08351","lon":"-97.65974"}},{"value":"Harlingen, Tex.","data":{"lat":"26.19063","lon":"-97.6961"}},{"value":"Harper Woods, Mich.","data":{"lat":"42.43309","lon":"-82.92408"}},{"value":"Harrisburg, Pa.","data":{"lat":"40.2737","lon":"-76.88442"}},{"value":"Harrisburg, N.C.","data":{"lat":"35.32375","lon":"-80.6559"}},{"value":"Harrison, N.Y.","data":{"lat":"40.96899","lon":"-73.71263"}},{"value":"Harrison, Ark.","data":{"lat":"36.22979","lon":"-93.10768"}},{"value":"Harrison, N.J.","data":{"lat":"40.74649","lon":"-74.15626"}},{"value":"Harrisonburg, Va.","data":{"lat":"38.44957","lon":"-78.86892"}},{"value":"Harrisonville, Mo.","data":{"lat":"38.65334","lon":"-94.34884"}},{"value":"Hartford, Wis.","data":{"lat":"43.31778","lon":"-88.37899"}},{"value":"Hartselle, Ala.","data":{"lat":"34.44343","lon":"-86.93528"}},{"value":"Harvey, Ill.","data":{"lat":"41.61003","lon":"-87.64671"}},{"value":"Harvey, La.","data":{"lat":"29.90354","lon":"-90.07729"}},{"value":"Harwich, Mass.","data":{"lat":"41.68622","lon":"-70.07585"}},{"value":"Hasbrouck Heights, N.J.","data":{"lat":"40.85816","lon":"-74.0807"}},{"value":"Haslett, Mich.","data":{"lat":"42.74698","lon":"-84.40108"}},{"value":"Hastings, Minn.","data":{"lat":"44.7433","lon":"-92.85243"}},{"value":"Hastings, Neb.","data":{"lat":"40.58612","lon":"-98.38839"}},{"value":"Hattiesburg, Miss.","data":{"lat":"31.32712","lon":"-89.29034"}},{"value":"Hauppauge, N.Y.","data":{"lat":"40.82565","lon":"-73.20261"}},{"value":"Havelock, N.C.","data":{"lat":"34.87905","lon":"-76.90133"}},{"value":"Haverhill, Mass.","data":{"lat":"42.7762","lon":"-71.07728"}},{"value":"Haverstraw, N.Y.","data":{"lat":"41.19759","lon":"-73.96458"}},{"value":"Havre de Grace, Md.","data":{"lat":"39.54928","lon":"-76.09162"}},{"value":"Hawaiian Gardens, Calif.","data":{"lat":"33.8314","lon":"-118.07284"}},{"value":"Hawaiian Paradise Park, Hawaii","data":{"lat":"19.59333","lon":"-154.97306"}},{"value":"Hawaiian Paradise Park, Hawaii","data":{"lat":"19.50139","lon":"-154.97056"}},{"value":"Hawthorne, Calif.","data":{"lat":"33.9164","lon":"-118.35257"}},{"value":"Hawthorne, N.J.","data":{"lat":"40.94926","lon":"-74.15375"}},{"value":"Hayden, Idaho","data":{"lat":"47.76602","lon":"-116.78658"}},{"value":"Hayesville, Ore.","data":{"lat":"44.98595","lon":"-122.98287"}},{"value":"Hays, Kan.","data":{"lat":"38.87918","lon":"-99.32677"}},{"value":"Haysville, Kan.","data":{"lat":"37.56446","lon":"-97.35227"}},{"value":"Hazel Crest, Ill.","data":{"lat":"41.5717","lon":"-87.69449"}},{"value":"Hazel Dell, Wash.","data":{"lat":"45.67151","lon":"-122.66288"}},{"value":"Hazel Park, Mich.","data":{"lat":"42.46254","lon":"-83.10409"}},{"value":"Hazelwood, Mo.","data":{"lat":"38.77144","lon":"-90.37095"}},{"value":"Hazleton, Pa.","data":{"lat":"40.95842","lon":"-75.97465"}},{"value":"Hackberry, La.","data":{"lat":"29.99605","lon":"-93.3421"}},{"value":"Hackettstown, N.J.","data":{"lat":"40.85399","lon":"-74.82906"}},{"value":"Hackleburg, Ala.","data":{"lat":"34.27732","lon":"-87.82864"}},{"value":"Haddon Heights, N.J.","data":{"lat":"39.87734","lon":"-75.06462"}},{"value":"Hadley, Mass.","data":{"lat":"42.34176","lon":"-72.58842"}},{"value":"Hadley, N.Y.","data":{"lat":"43.31729","lon":"-73.84818"}},{"value":"Hagaman, N.Y.","data":{"lat":"42.97452","lon":"-74.15096"}},{"value":"Hagerman, N.M.","data":{"lat":"33.11511","lon":"-104.32691"}},{"value":"Hagerstown, Ind.","data":{"lat":"39.91116","lon":"-85.16163"}},{"value":"Hahira, Ga.","data":{"lat":"30.99131","lon":"-83.37266"}},{"value":"Hahnville, La.","data":{"lat":"29.97659","lon":"-90.40897"}},{"value":"Haiku-Pauwela, Hawaii","data":{"lat":"20.92187","lon":"-156.30508"}},{"value":"Hailey, Idaho","data":{"lat":"43.51963","lon":"-114.31532"}},{"value":"Haines, Alaska","data":{"lat":"59.22859","lon":"-135.44411"}},{"value":"Hainesville, Ill.","data":{"lat":"42.34502","lon":"-88.06786"}},{"value":"Hale Center, Tex.","data":{"lat":"34.06424","lon":"-101.84379"}},{"value":"Hale'iwa, Hawaii","data":{"lat":"21.58849","lon":"-158.11051"}},{"value":"Haledon, N.J.","data":{"lat":"40.93565","lon":"-74.18626"}},{"value":"Hales Corners, Wis.","data":{"lat":"42.93752","lon":"-88.0487"}},{"value":"Halesite, N.Y.","data":{"lat":"40.88843","lon":"-73.4154"}},{"value":"Haleyville, Ala.","data":{"lat":"34.22649","lon":"-87.62141"}},{"value":"Half Moon, N.C.","data":{"lat":"34.826","lon":"-77.45941"}},{"value":"Halfway House, Pa.","data":{"lat":"40.28204","lon":"-75.64324"}},{"value":"Halifax, Va.","data":{"lat":"36.76597","lon":"-78.92834"}},{"value":"Halifax, Mass.","data":{"lat":"41.99121","lon":"-70.86198"}},{"value":"Hall Park, Okla.","data":{"lat":"35.23701","lon":"-97.40642"}},{"value":"Hallam, Pa.","data":{"lat":"40.00482","lon":"-76.60413"}},{"value":"Hallettsville, Tex.","data":{"lat":"29.44385","lon":"-96.94109"}},{"value":"Hallowell, Maine","data":{"lat":"44.2859","lon":"-69.79088"}},{"value":"Halls, Tenn.","data":{"lat":"35.87563","lon":"-89.39618"}},{"value":"Hallstead, Pa.","data":{"lat":"41.96119","lon":"-75.74324"}},{"value":"Hallsville, Tex.","data":{"lat":"32.50432","lon":"-94.57409"}},{"value":"Hallsville, Mo.","data":{"lat":"39.11699","lon":"-92.22074"}},{"value":"Halstead, Kan.","data":{"lat":"38.0014","lon":"-97.50865"}},{"value":"Hamburg, Pa.","data":{"lat":"40.55565","lon":"-75.98188"}},{"value":"Hamburg, N.Y.","data":{"lat":"42.71589","lon":"-78.82948"}},{"value":"Hamburg, Ark.","data":{"lat":"33.22818","lon":"-91.79763"}},{"value":"Hamburg, Iowa","data":{"lat":"40.60445","lon":"-95.65777"}},{"value":"Hamburg, N.J.","data":{"lat":"41.14848","lon":"-74.57348"}},{"value":"Hamilton, Mass.","data":{"lat":"42.2562","lon":"-71.76757"}},{"value":"Hamilton, Ill.","data":{"lat":"40.39643","lon":"-91.33904"}},{"value":"Hamilton, Mo.","data":{"lat":"39.74362","lon":"-93.99827"}},{"value":"Hamilton, Mont.","data":{"lat":"46.24687","lon":"-114.16037"}},{"value":"Hamilton, Ga.","data":{"lat":"32.75791","lon":"-84.87493"}},{"value":"Hamilton, Ala.","data":{"lat":"34.14232","lon":"-87.98864"}},{"value":"Hamilton, N.Y.","data":{"lat":"42.82701","lon":"-75.54462"}},{"value":"Hamilton, Ind.","data":{"lat":"41.53366","lon":"-84.91274"}},{"value":"Hamilton, Tex.","data":{"lat":"31.70377","lon":"-98.12392"}},{"value":"Hamilton City, Calif.","data":{"lat":"39.74266","lon":"-122.01359"}},{"value":"Hamlet, N.C.","data":{"lat":"34.88488","lon":"-79.69422"}},{"value":"Hamlin, Tex.","data":{"lat":"32.88483","lon":"-100.12649"}},{"value":"Hamlin, N.Y.","data":{"lat":"43.30312","lon":"-77.92112"}},{"value":"Hamlin, W.V.","data":{"lat":"38.2787","lon":"-82.10292"}},{"value":"Hammond, Wis.","data":{"lat":"44.97886","lon":"-92.43575"}},{"value":"Hampden, Maine","data":{"lat":"44.74452","lon":"-68.83698"}},{"value":"Hampden, Mass.","data":{"lat":"42.06398","lon":"-72.41342"}},{"value":"Hampden Sydney, Va.","data":{"lat":"37.24237","lon":"-78.45972"}},{"value":"Hampshire, Ill.","data":{"lat":"42.0978","lon":"-88.53036"}},{"value":"Hampstead, N.H.","data":{"lat":"42.87453","lon":"-71.18117"}},{"value":"Hampstead, N.C.","data":{"lat":"34.36767","lon":"-77.71053"}},{"value":"Hampstead, Md.","data":{"lat":"39.60483","lon":"-76.84998"}},{"value":"Hampton, S.C.","data":{"lat":"32.87794","lon":"-81.12761"}},{"value":"Hampton, Ill.","data":{"lat":"41.55587","lon":"-90.4093"}},{"value":"Hampton, Md.","data":{"lat":"39.42288","lon":"-76.58469"}},{"value":"Hampton, Ga.","data":{"lat":"33.38706","lon":"-84.28298"}},{"value":"Hampton, N.J.","data":{"lat":"40.70704","lon":"-74.956"}},{"value":"Hampton, N.H.","data":{"lat":"42.93759","lon":"-70.83894"}},{"value":"Hampton, Iowa","data":{"lat":"42.74192","lon":"-93.20242"}},{"value":"Hampton, Ark.","data":{"lat":"33.53789","lon":"-92.46988"}},{"value":"Hampton Beach, N.H.","data":{"lat":"42.90731","lon":"-70.812"}},{"value":"Hampton Falls, N.H.","data":{"lat":"42.9162","lon":"-70.86366"}},{"value":"Hampton Manor, N.Y.","data":{"lat":"42.62091","lon":"-73.72845"}},{"value":"Hana, Hawaii","data":{"lat":"20.75806","lon":"-155.99028"}},{"value":"Hanama'ulu, Hawaii","data":{"lat":"21.99319","lon":"-159.35416"}},{"value":"Hanapepe, Hawaii","data":{"lat":"21.90733","lon":"-159.5944"}},{"value":"Hanapepe Heights, Hawaii","data":{"lat":"21.91633","lon":"-159.58995"}},{"value":"Hanceville, Ala.","data":{"lat":"34.06065","lon":"-86.7675"}},{"value":"Hancock, N.Y.","data":{"lat":"41.95398","lon":"-75.28045"}},{"value":"Hancock, Md.","data":{"lat":"39.69898","lon":"-78.17973"}},{"value":"Hancock, Maine","data":{"lat":"44.52924","lon":"-68.25363"}},{"value":"Hancock, Mich.","data":{"lat":"47.12687","lon":"-88.58096"}},{"value":"Hanley Hills, Mo.","data":{"lat":"38.68588","lon":"-90.32373"}},{"value":"Hanna City, Ill.","data":{"lat":"40.6917","lon":"-89.79511"}},{"value":"Hannahs Mill, Ga.","data":{"lat":"32.93291","lon":"-84.34936"}},{"value":"Hannawa Falls, N.Y.","data":{"lat":"44.61228","lon":"-74.97103"}},{"value":"Hanover, N.H.","data":{"lat":"43.70229","lon":"-72.28954"}},{"value":"Hanover, Ind.","data":{"lat":"38.71423","lon":"-85.47357"}},{"value":"Hanover, Minn.","data":{"lat":"45.1558","lon":"-93.66635"}},{"value":"Hansen, Idaho","data":{"lat":"42.53068","lon":"-114.30101"}},{"value":"Hanson, Mass.","data":{"lat":"42.0751","lon":"-70.88004"}},{"value":"Hansville, Wash.","data":{"lat":"47.9187","lon":"-122.55431"}},{"value":"Hapeville, Ga.","data":{"lat":"33.66011","lon":"-84.4102"}},{"value":"Happy Camp, Calif.","data":{"lat":"41.79318","lon":"-123.3795"}},{"value":"Harahan, La.","data":{"lat":"29.94048","lon":"-90.20313"}},{"value":"Harbison Canyon, Calif.","data":{"lat":"32.82033","lon":"-116.83002"}},{"value":"Harbor, Ore.","data":{"lat":"42.05317","lon":"-124.26759"}},{"value":"Harbor Beach, Mich.","data":{"lat":"43.84474","lon":"-82.65132"}},{"value":"Harbor Bluffs, Fla.","data":{"lat":"27.90947","lon":"-82.8276"}},{"value":"Harbor Hills, Ohio","data":{"lat":"39.93673","lon":"-82.43515"}},{"value":"Harbor Isle, N.Y.","data":{"lat":"40.60344","lon":"-73.66457"}},{"value":"Harbor Springs, Mich.","data":{"lat":"45.43168","lon":"-84.992"}},{"value":"Harbour Heights, Fla.","data":{"lat":"26.99089","lon":"-82.00231"}},{"value":"Hardeeville, S.C.","data":{"lat":"32.28714","lon":"-81.08067"}},{"value":"Hardin, Mont.","data":{"lat":"45.73248","lon":"-107.61203"}},{"value":"Hardinsburg, Ky.","data":{"lat":"37.78006","lon":"-86.46053"}},{"value":"Hardwick, N.J.","data":{"lat":"41.05454","lon":"-74.93212"}},{"value":"Hardwick, Ga.","data":{"lat":"33.0682","lon":"-83.22349"}},{"value":"Hardwick, Mass.","data":{"lat":"42.35009","lon":"-72.19952"}},{"value":"Hardwick, Vt.","data":{"lat":"44.50478","lon":"-72.36816"}},{"value":"Harkers Island, N.C.","data":{"lat":"34.69516","lon":"-76.55937"}},{"value":"Harlan, Ind.","data":{"lat":"41.19616","lon":"-84.91969"}},{"value":"Harlan, Iowa","data":{"lat":"41.65304","lon":"-95.32555"}},{"value":"Harlan, Ky.","data":{"lat":"36.84314","lon":"-83.32185"}},{"value":"Harleigh, Pa.","data":{"lat":"40.98064","lon":"-75.97131"}},{"value":"Harlem, Ga.","data":{"lat":"33.41458","lon":"-82.31262"}},{"value":"Harlem, Fla.","data":{"lat":"26.73757","lon":"-80.9509"}},{"value":"Harlem Heights, Fla.","data":{"lat":"26.51619","lon":"-81.92787"}},{"value":"Harleysville, Pa.","data":{"lat":"40.27955","lon":"-75.38712"}},{"value":"Harmony, Minn.","data":{"lat":"43.55524","lon":"-92.01016"}},{"value":"Harper, Kan.","data":{"lat":"37.28669","lon":"-98.02589"}},{"value":"Harper, Tex.","data":{"lat":"30.29992","lon":"-99.24421"}},{"value":"Harpersville, Ala.","data":{"lat":"33.344","lon":"-86.43804"}},{"value":"Harpswell Center, Maine","data":{"lat":"43.80175","lon":"-69.98421"}},{"value":"Harrah, Okla.","data":{"lat":"35.48951","lon":"-97.16364"}},{"value":"Harriman, N.Y.","data":{"lat":"41.30843","lon":"-74.14459"}},{"value":"Harriman, Tenn.","data":{"lat":"35.93396","lon":"-84.55244"}},{"value":"Harrington, Del.","data":{"lat":"38.92372","lon":"-75.5777"}},{"value":"Harrington Park, N.J.","data":{"lat":"40.98371","lon":"-73.97986"}},{"value":"Harris, Minn.","data":{"lat":"45.58635","lon":"-92.97466"}},{"value":"Harris Hill, N.Y.","data":{"lat":"42.96478","lon":"-78.67753"}},{"value":"Harrisburg, Ore.","data":{"lat":"44.27401","lon":"-123.17065"}},{"value":"Harrisburg, Ark.","data":{"lat":"35.56425","lon":"-90.71678"}},{"value":"Harrisburg, Ill.","data":{"lat":"37.73838","lon":"-88.54061"}},{"value":"Harrisburg, S.D.","data":{"lat":"43.43137","lon":"-96.69727"}},{"value":"Harrison, Maine","data":{"lat":"44.11035","lon":"-70.67923"}},{"value":"Harrison, Mich.","data":{"lat":"44.01919","lon":"-84.79947"}},{"value":"Harrison, Tenn.","data":{"lat":"35.11368","lon":"-85.13801"}},{"value":"Harrison, Ohio","data":{"lat":"39.262","lon":"-84.81995"}},{"value":"Harristown, Ill.","data":{"lat":"39.85393","lon":"-89.08397"}},{"value":"Harrisville, R.I.","data":{"lat":"41.96565","lon":"-71.67451"}},{"value":"Harrisville, W.V.","data":{"lat":"39.20952","lon":"-81.05178"}},{"value":"Harrisville, N.H.","data":{"lat":"42.94508","lon":"-72.09647"}},{"value":"Harrisville, Utah","data":{"lat":"41.28133","lon":"-111.98828"}},{"value":"Harrodsburg, Ky.","data":{"lat":"37.7623","lon":"-84.84329"}},{"value":"Harrogate, Tenn.","data":{"lat":"36.5823","lon":"-83.65686"}},{"value":"Hart, Mich.","data":{"lat":"43.69834","lon":"-86.36397"}},{"value":"Hart, Tex.","data":{"lat":"34.38507","lon":"-102.11574"}},{"value":"Hartford, Maine","data":{"lat":"44.37284","lon":"-70.34673"}},{"value":"Hartford, S.D.","data":{"lat":"43.62303","lon":"-96.94256"}},{"value":"Hartford, Ky.","data":{"lat":"37.45116","lon":"-86.90916"}},{"value":"Hartford, Ala.","data":{"lat":"31.1024","lon":"-85.69688"}},{"value":"Hartford, Ill.","data":{"lat":"38.83338","lon":"-90.09594"}},{"value":"Hartford, Mich.","data":{"lat":"42.20671","lon":"-86.16669"}},{"value":"Hartford City, Ind.","data":{"lat":"40.45115","lon":"-85.36997"}},{"value":"Hartington, Neb.","data":{"lat":"42.6225","lon":"-97.2645"}},{"value":"Hartland, Wis.","data":{"lat":"43.10501","lon":"-88.34204"}},{"value":"Hartley, Calif.","data":{"lat":"38.41713","lon":"-121.94691"}},{"value":"Hartley, Iowa","data":{"lat":"43.17997","lon":"-95.47695"}},{"value":"Hartsdale, N.Y.","data":{"lat":"41.01899","lon":"-73.79819"}},{"value":"Hartshorne, Okla.","data":{"lat":"34.8451","lon":"-95.55748"}},{"value":"Hartsville, S.C.","data":{"lat":"34.37404","lon":"-80.0734"}},{"value":"Hartsville, Tenn.","data":{"lat":"36.39088","lon":"-86.16721"}},{"value":"Hartville, Ohio","data":{"lat":"40.96367","lon":"-81.33122"}},{"value":"Hartwell, Ga.","data":{"lat":"34.35288","lon":"-82.93209"}},{"value":"Harvard, Ill.","data":{"lat":"42.42224","lon":"-88.61371"}},{"value":"Harvard, Mass.","data":{"lat":"42.50009","lon":"-71.58284"}},{"value":"Harvard, Neb.","data":{"lat":"40.6189","lon":"-98.09727"}},{"value":"Harvest, Ala.","data":{"lat":"34.85564","lon":"-86.75083"}},{"value":"Harvey, Mich.","data":{"lat":"46.49466","lon":"-87.35431"}},{"value":"Harvey, N.D.","data":{"lat":"47.76972","lon":"-99.9354"}},{"value":"Harveys Lake, Pa.","data":{"lat":"41.38341","lon":"-76.02465"}},{"value":"Harwich Center, Mass.","data":{"lat":"41.69235","lon":"-70.06938"}},{"value":"Harwich Port, Mass.","data":{"lat":"41.66678","lon":"-70.07863"}},{"value":"Harwood Heights, Ill.","data":{"lat":"41.96725","lon":"-87.80756"}},{"value":"Haskell, Tex.","data":{"lat":"33.1576","lon":"-99.7337"}},{"value":"Haskell, Ark.","data":{"lat":"34.50148","lon":"-92.63655"}},{"value":"Haskell, Okla.","data":{"lat":"35.82038","lon":"-95.67415"}},{"value":"Haskins, Ohio","data":{"lat":"41.46477","lon":"-83.70605"}},{"value":"Haslet, Tex.","data":{"lat":"32.97485","lon":"-97.3478"}},{"value":"Hasson Heights, Pa.","data":{"lat":"41.44895","lon":"-79.677"}},{"value":"Hastings, Mich.","data":{"lat":"42.64587","lon":"-85.29084"}},{"value":"Hastings, Pa.","data":{"lat":"40.66507","lon":"-78.71225"}},{"value":"Hastings-on-Hudson, N.Y.","data":{"lat":"40.99454","lon":"-73.87875"}},{"value":"Hatboro, Pa.","data":{"lat":"40.17428","lon":"-75.10684"}},{"value":"Hatch, N.M.","data":{"lat":"32.66536","lon":"-107.15307"}},{"value":"Hatfield, Pa.","data":{"lat":"40.27983","lon":"-75.29934"}},{"value":"Hatfield, Mass.","data":{"lat":"42.37092","lon":"-72.59814"}},{"value":"Hau'ula, Hawaii","data":{"lat":"21.6076","lon":"-157.90868"}},{"value":"Haubstadt, Ind.","data":{"lat":"38.20504","lon":"-87.57419"}},{"value":"Haughton, La.","data":{"lat":"32.53265","lon":"-93.50406"}},{"value":"Havana, Fla.","data":{"lat":"30.62381","lon":"-84.41463"}},{"value":"Havana, Ill.","data":{"lat":"40.30004","lon":"-90.06095"}},{"value":"Haven, Kan.","data":{"lat":"37.8989","lon":"-97.78283"}},{"value":"Haverhill, N.H.","data":{"lat":"44.03451","lon":"-72.06398"}},{"value":"Haverhill, Fla.","data":{"lat":"26.69118","lon":"-80.12004"}},{"value":"Haviland, N.Y.","data":{"lat":"41.76676","lon":"-73.90152"}},{"value":"Havre, Mont.","data":{"lat":"48.55","lon":"-109.68409"}},{"value":"Haw River, N.C.","data":{"lat":"36.09153","lon":"-79.36419"}},{"value":"Hawaiian Acres, Hawaii","data":{"lat":"19.53806","lon":"-155.05222"}},{"value":"Hawaiian Beaches, Hawaii","data":{"lat":"19.54306","lon":"-154.91583"}},{"value":"Hawaiian Ocean View, Hawaii","data":{"lat":"19.06861","lon":"-155.765"}},{"value":"Hawarden, Iowa","data":{"lat":"42.99582","lon":"-96.48531"}},{"value":"Hawi, Hawaii","data":{"lat":"20.24139","lon":"-155.83278"}},{"value":"Hawkins, Tex.","data":{"lat":"32.58847","lon":"-95.20411"}},{"value":"Hawkinsville, Ga.","data":{"lat":"32.28377","lon":"-83.47212"}},{"value":"Hawley, Pa.","data":{"lat":"41.47592","lon":"-75.18212"}},{"value":"Hawley, Minn.","data":{"lat":"46.88079","lon":"-96.31673"}},{"value":"Haworth, N.J.","data":{"lat":"40.96093","lon":"-73.99014"}},{"value":"Hawthorn Woods, Ill.","data":{"lat":"42.21697","lon":"-88.04952"}},{"value":"Hawthorne, Nev.","data":{"lat":"38.52464","lon":"-118.62458"}},{"value":"Hawthorne, Fla.","data":{"lat":"28.76138","lon":"-81.87091"}},{"value":"Hawthorne, N.Y.","data":{"lat":"41.10732","lon":"-73.79597"}},{"value":"Hawthorne, Fla.","data":{"lat":"29.59191","lon":"-82.08732"}},{"value":"Hayden, Colo.","data":{"lat":"40.49529","lon":"-107.25729"}},{"value":"Hayfield, Va.","data":{"lat":"38.75178","lon":"-77.13581"}},{"value":"Hayfield, Minn.","data":{"lat":"43.89052","lon":"-92.84769"}},{"value":"Hayfork, Calif.","data":{"lat":"40.55431","lon":"-123.18308"}},{"value":"Haymarket, Va.","data":{"lat":"38.81206","lon":"-77.63638"}},{"value":"Haynesville, La.","data":{"lat":"32.96208","lon":"-93.14016"}},{"value":"Hays, N.C.","data":{"lat":"36.24985","lon":"-81.11564"}},{"value":"Hayti, Mo.","data":{"lat":"36.23368","lon":"-89.74953"}},{"value":"Hayward, Wis.","data":{"lat":"46.01301","lon":"-91.48462"}},{"value":"Hazard, Ky.","data":{"lat":"37.24954","lon":"-83.19323"}},{"value":"Hazardville, Conn.","data":{"lat":"41.98732","lon":"-72.54481"}},{"value":"Hazel Green, Wis.","data":{"lat":"42.53278","lon":"-90.43457"}},{"value":"Hazel Green, Ala.","data":{"lat":"34.93231","lon":"-86.57194"}},{"value":"Hazelwood, N.C.","data":{"lat":"35.46871","lon":"-83.00403"}},{"value":"Hazen, Ark.","data":{"lat":"34.78093","lon":"-91.58097"}},{"value":"Hazen, N.D.","data":{"lat":"47.29445","lon":"-101.62266"}},{"value":"Hazlehurst, Miss.","data":{"lat":"31.86044","lon":"-90.39593"}},{"value":"Hazlehurst, Ga.","data":{"lat":"31.86963","lon":"-82.5943"}},{"value":"Ha'ena, Hawaii","data":{"lat":"22.22135","lon":"-159.56129"}},{"value":"Hackberry, Tex.","data":{"lat":"33.15234","lon":"-96.91778"}},{"value":"Hackberry, Tex.","data":{"lat":"29.57829","lon":"-96.8797"}},{"value":"Hackensack, Minn.","data":{"lat":"46.93079","lon":"-94.52055"}},{"value":"Hackett, Ark.","data":{"lat":"35.19037","lon":"-94.41105"}},{"value":"Hackneyville, Ala.","data":{"lat":"33.0604","lon":"-85.93302"}},{"value":"Hadar, Neb.","data":{"lat":"42.105","lon":"-97.44922"}},{"value":"Haddam, Kan.","data":{"lat":"39.85695","lon":"-97.3017"}},{"value":"Hagan, Ga.","data":{"lat":"32.15603","lon":"-81.93373"}},{"value":"Hagarville, Ark.","data":{"lat":"35.51564","lon":"-93.3249"}},{"value":"Hager City, Wis.","data":{"lat":"44.60163","lon":"-92.53825"}},{"value":"Hagerman, Idaho","data":{"lat":"42.81212","lon":"-114.89867"}},{"value":"Haigler, Neb.","data":{"lat":"40.01388","lon":"-101.93935"}},{"value":"Hailesboro, N.Y.","data":{"lat":"44.31006","lon":"-75.44632"}},{"value":"Haileyville, Okla.","data":{"lat":"34.85454","lon":"-95.5822"}},{"value":"Haines, Ore.","data":{"lat":"44.91153","lon":"-117.93883"}},{"value":"Hala'ula, Hawaii","data":{"lat":"20.2375","lon":"-155.78056"}},{"value":"Halbur, Iowa","data":{"lat":"42.00693","lon":"-94.96999"}},{"value":"Halchita, Utah","data":{"lat":"37.12584","lon":"-109.88846"}},{"value":"Hale, Mo.","data":{"lat":"39.60363","lon":"-93.34243"}},{"value":"Haleburg, Ala.","data":{"lat":"31.40656","lon":"-85.13715"}},{"value":"Halfway, Mo.","data":{"lat":"37.61643","lon":"-93.24464"}},{"value":"Halfway, Ore.","data":{"lat":"44.88072","lon":"-117.11462"}},{"value":"Halifax, N.C.","data":{"lat":"36.32849","lon":"-77.58942"}},{"value":"Halifax, Pa.","data":{"lat":"40.46814","lon":"-76.93192"}},{"value":"Haliimaile, Hawaii","data":{"lat":"20.87111","lon":"-156.34389"}},{"value":"Hall, N.Y.","data":{"lat":"42.79396","lon":"-77.06636"}},{"value":"Hall Summit, La.","data":{"lat":"32.17738","lon":"-93.30239"}},{"value":"Hallam, Neb.","data":{"lat":"40.53778","lon":"-96.78725"}},{"value":"Hallett, Okla.","data":{"lat":"36.23396","lon":"-96.56753"}},{"value":"Halliday, N.D.","data":{"lat":"47.35445","lon":"-102.33601"}},{"value":"Hallock, Minn.","data":{"lat":"48.77443","lon":"-96.94645"}},{"value":"Hallsboro, N.C.","data":{"lat":"34.32239","lon":"-78.5989"}},{"value":"Hallsburg, Tex.","data":{"lat":"31.53878","lon":"-96.95611"}},{"value":"Halltown, Mo.","data":{"lat":"37.19338","lon":"-93.62548"}},{"value":"Hallwood, Va.","data":{"lat":"37.87763","lon":"-75.58909"}},{"value":"Halsey, Ore.","data":{"lat":"44.38401","lon":"-123.10981"}},{"value":"Halstad, Minn.","data":{"lat":"47.35164","lon":"-96.82869"}},{"value":"Hambleton, W.V.","data":{"lat":"39.08205","lon":"-79.64534"}},{"value":"Hamburg, Ill.","data":{"lat":"39.23005","lon":"-90.71762"}},{"value":"Hamburg, Minn.","data":{"lat":"44.7333","lon":"-93.96719"}},{"value":"Hamden, Ohio","data":{"lat":"39.15979","lon":"-82.52683"}},{"value":"Hamel, Ill.","data":{"lat":"38.88894","lon":"-89.84538"}},{"value":"Hamersville, Ohio","data":{"lat":"38.91785","lon":"-83.98326"}},{"value":"Hamilton, Kan.","data":{"lat":"37.97947","lon":"-96.16416"}},{"value":"Hamilton, Iowa","data":{"lat":"41.16917","lon":"-92.90326"}},{"value":"Hamilton, N.C.","data":{"lat":"35.9446","lon":"-77.20968"}},{"value":"Hamilton, Miss.","data":{"lat":"33.74039","lon":"-88.41115"}},{"value":"Hamilton, Va.","data":{"lat":"39.13427","lon":"-77.66249"}},{"value":"Hamilton, Wash.","data":{"lat":"48.5215","lon":"-121.98931"}},{"value":"Hamilton Branch, Calif.","data":{"lat":"40.27489","lon":"-121.09135"}},{"value":"Hamler, Ohio","data":{"lat":"41.22922","lon":"-84.03411"}},{"value":"Hamlet, Ind.","data":{"lat":"41.54754","lon":"-86.58224"}},{"value":"Hamlin, Maine","data":{"lat":"47.06588","lon":"-67.79391"}},{"value":"Hammon, Okla.","data":{"lat":"35.63283","lon":"-99.38177"}},{"value":"Hammond, Minn.","data":{"lat":"44.22219","lon":"-92.37351"}},{"value":"Hammond, Ill.","data":{"lat":"39.79698","lon":"-88.59173"}},{"value":"Hammond, Ore.","data":{"lat":"46.2001","lon":"-123.95154"}},{"value":"Hammond, N.Y.","data":{"lat":"44.44895","lon":"-75.69412"}},{"value":"Hammondsport, N.Y.","data":{"lat":"42.40785","lon":"-77.22359"}},{"value":"Hammondville, Ala.","data":{"lat":"34.58175","lon":"-85.62663"}},{"value":"Hampton, Minn.","data":{"lat":"44.61024","lon":"-93.00216"}},{"value":"Hampton, N.Y.","data":{"lat":"43.52479","lon":"-73.25178"}},{"value":"Hampton, Neb.","data":{"lat":"40.8789","lon":"-97.88589"}},{"value":"Hampton, Pa.","data":{"lat":"39.92954","lon":"-77.05831"}},{"value":"Hampton, Fla.","data":{"lat":"29.86441","lon":"-82.13094"}},{"value":"Hanalei, Hawaii","data":{"lat":"22.20169","lon":"-159.50312"}},{"value":"Hancock, Iowa","data":{"lat":"41.38999","lon":"-95.3625"}},{"value":"Hancock, Minn.","data":{"lat":"45.49746","lon":"-95.79671"}},{"value":"Hancock, Wis.","data":{"lat":"44.13358","lon":"-89.52318"}},{"value":"Hancock, Mass.","data":{"lat":"42.54314","lon":"-73.32372"}},{"value":"Hancock, N.H.","data":{"lat":"42.97286","lon":"-71.9798"}},{"value":"Hancocks Bridge, N.J.","data":{"lat":"39.50539","lon":"-75.46187"}},{"value":"Handley, W.V.","data":{"lat":"38.18705","lon":"-81.36539"}},{"value":"Hanging Rock, Ohio","data":{"lat":"38.56008","lon":"-82.721"}},{"value":"Hankinson, N.D.","data":{"lat":"46.06968","lon":"-96.90175"}},{"value":"Hanksville, Utah","data":{"lat":"38.37304","lon":"-110.71404"}},{"value":"Hanley Falls, Minn.","data":{"lat":"44.69274","lon":"-95.62196"}},{"value":"Hanlontown, Iowa","data":{"lat":"43.28023","lon":"-93.37882"}},{"value":"Hanna, Ind.","data":{"lat":"41.41199","lon":"-86.78002"}},{"value":"Hanna, Okla.","data":{"lat":"35.2051","lon":"-95.89028"}},{"value":"Hanna, Wyo.","data":{"lat":"41.86996","lon":"-106.56197"}},{"value":"Hannaford, N.D.","data":{"lat":"47.31333","lon":"-98.18648"}},{"value":"Hannasville, Pa.","data":{"lat":"41.47783","lon":"-79.94784"}},{"value":"Hannibal, Ohio","data":{"lat":"39.6673","lon":"-80.87204"}},{"value":"Hannibal, N.Y.","data":{"lat":"43.32118","lon":"-76.57883"}},{"value":"Hanover, Kan.","data":{"lat":"39.89389","lon":"-96.87947"}},{"value":"Hanover, Ohio","data":{"lat":"40.07979","lon":"-82.26098"}},{"value":"Hanover, Va.","data":{"lat":"37.76653","lon":"-77.37026"}},{"value":"Hanover, Mich.","data":{"lat":"42.10115","lon":"-84.5519"}},{"value":"Hanover, Maine","data":{"lat":"44.49673","lon":"-70.69424"}},{"value":"Hanover, Ill.","data":{"lat":"42.25641","lon":"-90.27957"}},{"value":"Hanover, N.M.","data":{"lat":"32.81341","lon":"-108.09115"}},{"value":"Hanover, Wis.","data":{"lat":"42.63862","lon":"-89.16206"}},{"value":"Hanoverton, Ohio","data":{"lat":"40.75117","lon":"-80.93703"}},{"value":"Hanska, Minn.","data":{"lat":"44.14885","lon":"-94.49414"}},{"value":"Hanson, Ky.","data":{"lat":"37.41727","lon":"-87.48083"}},{"value":"Hanston, Kan.","data":{"lat":"38.12196","lon":"-99.7129"}},{"value":"Happy, Tex.","data":{"lat":"34.74367","lon":"-101.85463"}},{"value":"Happy Valley, Alaska","data":{"lat":"59.94722","lon":"-151.73222"}},{"value":"Happys Inn, Mont.","data":{"lat":"48.08328","lon":"-115.14043"}},{"value":"Haralson, Ga.","data":{"lat":"33.22651","lon":"-84.57132"}},{"value":"Harbor Hills, N.Y.","data":{"lat":"40.79093","lon":"-73.74652"}},{"value":"Harbor View, Ohio","data":{"lat":"41.69338","lon":"-83.44438"}},{"value":"Harborton, Va.","data":{"lat":"37.6618","lon":"-75.83049"}},{"value":"Harcourt, Iowa","data":{"lat":"42.26275","lon":"-94.17579"}},{"value":"Hardesty, Okla.","data":{"lat":"36.61642","lon":"-101.19071"}},{"value":"Hardin, Mo.","data":{"lat":"39.27085","lon":"-93.83439"}},{"value":"Hardin, Tex.","data":{"lat":"30.15243","lon":"-94.73909"}},{"value":"Hardin, Ky.","data":{"lat":"36.76478","lon":"-88.29531"}},{"value":"Hardin, Ill.","data":{"lat":"39.15671","lon":"-90.6179"}},{"value":"Harding, Minn.","data":{"lat":"46.11608","lon":"-94.04082"}},{"value":"Harding-Birch Lakes, Alaska","data":{"lat":"64.3714","lon":"-146.5991"}},{"value":"Hardinsburg, Ind.","data":{"lat":"38.46089","lon":"-86.27859"}},{"value":"Hardtner, Kan.","data":{"lat":"37.01392","lon":"-98.64953"}},{"value":"Hardwick, Calif.","data":{"lat":"36.40134","lon":"-119.71874"}},{"value":"Hardwick, Minn.","data":{"lat":"43.77497","lon":"-96.19947"}},{"value":"Hardy, Ark.","data":{"lat":"36.3159","lon":"-91.48264"}},{"value":"Hardy, Neb.","data":{"lat":"40.0089","lon":"-97.92699"}},{"value":"Hardyville, Ky.","data":{"lat":"37.25422","lon":"-85.78608"}},{"value":"Hargill, Tex.","data":{"lat":"26.44257","lon":"-98.01389"}},{"value":"Haring, Mich.","data":{"lat":"44.29862","lon":"-85.41311"}},{"value":"Harlem, Mont.","data":{"lat":"48.53333","lon":"-108.78405"}},{"value":"Harleyville, S.C.","data":{"lat":"33.21461","lon":"-80.44787"}},{"value":"Harlingen, N.J.","data":{"lat":"40.4476","lon":"-74.66238"}},{"value":"Harlowton, Mont.","data":{"lat":"46.43551","lon":"-109.83435"}},{"value":"Harman, W.V.","data":{"lat":"38.92233","lon":"-79.52505"}},{"value":"Harmon, N.D.","data":{"lat":"46.95166","lon":"-100.95264"}},{"value":"Harmon, Ill.","data":{"lat":"41.72281","lon":"-89.55399"}},{"value":"Harmonsburg, Pa.","data":{"lat":"41.66089","lon":"-80.31784"}},{"value":"Harmony, Pa.","data":{"lat":"40.80145","lon":"-80.12728"}},{"value":"Harmony, Maine","data":{"lat":"44.97395","lon":"-69.54616"}},{"value":"Harmony, N.C.","data":{"lat":"35.95569","lon":"-80.77173"}},{"value":"Harmony, Ind.","data":{"lat":"39.53671","lon":"-87.10585"}},{"value":"Harmony, N.J.","data":{"lat":"40.74676","lon":"-75.1374"}},{"value":"Harmony, R.I.","data":{"lat":"41.88788","lon":"-71.59673"}},{"value":"Harold, Fla.","data":{"lat":"30.65908","lon":"-86.88024"}},{"value":"Harper, Ore.","data":{"lat":"43.86321","lon":"-117.60991"}},{"value":"Harper, Iowa","data":{"lat":"41.36251","lon":"-92.05101"}},{"value":"Harpers Ferry, W.V.","data":{"lat":"39.32538","lon":"-77.73888"}},{"value":"Harpers Ferry, Iowa","data":{"lat":"43.20054","lon":"-91.15319"}},{"value":"Harpster, Ohio","data":{"lat":"40.73922","lon":"-83.25381"}},{"value":"Harrah, Wash.","data":{"lat":"46.40429","lon":"-120.54423"}},{"value":"Harrell, Ark.","data":{"lat":"33.51011","lon":"-92.39876"}},{"value":"Harrells, N.C.","data":{"lat":"34.72767","lon":"-78.20111"}},{"value":"Harrellsville, N.C.","data":{"lat":"36.30266","lon":"-76.79245"}},{"value":"Harrietta, Mich.","data":{"lat":"44.31001","lon":"-85.69784"}},{"value":"Harrington, Wash.","data":{"lat":"47.48099","lon":"-118.25442"}},{"value":"Harrington, Maine","data":{"lat":"44.61924","lon":"-67.81028"}},{"value":"Harris, Iowa","data":{"lat":"43.44524","lon":"-95.43417"}},{"value":"Harrisburg, Ohio","data":{"lat":"39.80951","lon":"-83.17102"}},{"value":"Harrisburg, Mo.","data":{"lat":"39.1417","lon":"-92.46268"}},{"value":"Harrison, Ill.","data":{"lat":"37.79672","lon":"-89.33703"}},{"value":"Harrison, Ga.","data":{"lat":"32.82627","lon":"-82.72514"}},{"value":"Harrison, Mont.","data":{"lat":"45.70076","lon":"-111.78637"}},{"value":"Harrison, Neb.","data":{"lat":"42.68719","lon":"-103.88271"}},{"value":"Harrison, Idaho","data":{"lat":"47.45435","lon":"-116.78546"}},{"value":"Harrison City, Pa.","data":{"lat":"40.35424","lon":"-79.64838"}},{"value":"Harrisonburg, La.","data":{"lat":"31.77211","lon":"-91.82152"}},{"value":"Harriston, Va.","data":{"lat":"38.21735","lon":"-78.83225"}},{"value":"Harrisville, Mich.","data":{"lat":"44.6564","lon":"-83.29469"}},{"value":"Harrisville, N.Y.","data":{"lat":"44.15201","lon":"-75.32103"}},{"value":"Harrisville, N.Y.","data":{"lat":"42.68007","lon":"-75.46295"}},{"value":"Harrisville, Pa.","data":{"lat":"41.13673","lon":"-80.00922"}},{"value":"Harrisville, Ohio","data":{"lat":"40.18146","lon":"-80.88759"}},{"value":"Harrod, Ohio","data":{"lat":"40.70644","lon":"-83.92133"}},{"value":"Harrodsburg, Ind.","data":{"lat":"39.01338","lon":"-86.545"}},{"value":"Harrold, S.D.","data":{"lat":"44.52443","lon":"-99.73928"}},{"value":"Hartford, Ohio","data":{"lat":"41.31144","lon":"-80.56841"}},{"value":"Hartford, Kan.","data":{"lat":"38.30835","lon":"-95.95582"}},{"value":"Hartford, Ark.","data":{"lat":"35.02288","lon":"-94.38133"}},{"value":"Hartford, Iowa","data":{"lat":"41.45944","lon":"-93.40493"}},{"value":"Hartford City, W.V.","data":{"lat":"39.00397","lon":"-81.98903"}},{"value":"Hartland, Maine","data":{"lat":"44.88339","lon":"-69.44755"}},{"value":"Hartland, Minn.","data":{"lat":"43.80385","lon":"-93.48688"}},{"value":"Hartland, Vt.","data":{"lat":"43.54063","lon":"-72.39898"}},{"value":"Hartleton, Pa.","data":{"lat":"40.90063","lon":"-77.15609"}},{"value":"Hartley, Tex.","data":{"lat":"35.88559","lon":"-102.39686"}},{"value":"Hartline, Wash.","data":{"lat":"47.69043","lon":"-119.10835"}},{"value":"Hartman, Ark.","data":{"lat":"35.43258","lon":"-93.61547"}},{"value":"Hartrandt, Wyo.","data":{"lat":"42.88747","lon":"-106.34753"}},{"value":"Harts, W.V.","data":{"lat":"38.03121","lon":"-82.1293"}},{"value":"Hartsburg, Mo.","data":{"lat":"38.69503","lon":"-92.3088"}},{"value":"Hartsburg, Ill.","data":{"lat":"40.25088","lon":"-89.44093"}},{"value":"Hartstown, Pa.","data":{"lat":"41.55255","lon":"-80.37923"}},{"value":"Hartsville, Ind.","data":{"lat":"39.26755","lon":"-85.69804"}},{"value":"Hartville, Mo.","data":{"lat":"37.25088","lon":"-92.51044"}},{"value":"Hartwick, N.Y.","data":{"lat":"42.6598","lon":"-75.04877"}},{"value":"Harvel, Ill.","data":{"lat":"39.35616","lon":"-89.53232"}},{"value":"Harvey, Iowa","data":{"lat":"41.31583","lon":"-92.92409"}},{"value":"Harvey Cedars, N.J.","data":{"lat":"39.70623","lon":"-74.13403"}},{"value":"Harveysburg, Ohio","data":{"lat":"39.50367","lon":"-84.01049"}},{"value":"Harveyville, Kan.","data":{"lat":"38.79001","lon":"-95.96166"}},{"value":"Harviell, Mo.","data":{"lat":"36.66478","lon":"-90.47233"}},{"value":"Harwick, Pa.","data":{"lat":"40.55673","lon":"-79.80505"}},{"value":"Harwood, N.D.","data":{"lat":"46.97941","lon":"-96.88064"}},{"value":"Hastings, Fla.","data":{"lat":"29.71802","lon":"-81.50813"}},{"value":"Hastings, Okla.","data":{"lat":"34.22676","lon":"-98.11004"}},{"value":"Hastings, Iowa","data":{"lat":"41.02278","lon":"-95.49916"}},{"value":"Hasty, Colo.","data":{"lat":"38.11251","lon":"-102.95742"}},{"value":"Hat Creek, Calif.","data":{"lat":"40.83044","lon":"-121.51359"}},{"value":"Hatch, Utah","data":{"lat":"37.6497","lon":"-112.43437"}},{"value":"Hatfield, Wis.","data":{"lat":"44.41468","lon":"-90.7307"}},{"value":"Hatfield, Ark.","data":{"lat":"34.48566","lon":"-94.37855"}},{"value":"Hatfield, Ind.","data":{"lat":"37.90255","lon":"-87.22417"}},{"value":"Hatley, Miss.","data":{"lat":"33.97678","lon":"-88.4206"}},{"value":"Hatley, Wis.","data":{"lat":"44.88747","lon":"-89.33873"}},{"value":"Hatteras, N.C.","data":{"lat":"35.21934","lon":"-75.69016"}},{"value":"Hatton, Ala.","data":{"lat":"34.56287","lon":"-87.4153"}},{"value":"Hatton, Wash.","data":{"lat":"46.77597","lon":"-118.82639"}},{"value":"Hatton, N.D.","data":{"lat":"47.63971","lon":"-97.45342"}},{"value":"Haugen, Wis.","data":{"lat":"45.60884","lon":"-91.77489"}},{"value":"Hauser, Idaho","data":{"lat":"47.77498","lon":"-117.02808"}},{"value":"Havana, Ark.","data":{"lat":"35.1112","lon":"-93.52963"}},{"value":"Havana, Kan.","data":{"lat":"37.09174","lon":"-95.94193"}},{"value":"Havana, Tex.","data":{"lat":"26.24507","lon":"-98.50947"}},{"value":"Havelock, Iowa","data":{"lat":"42.83608","lon":"-94.70054"}},{"value":"Havensville, Kan.","data":{"lat":"39.51111","lon":"-96.07805"}},{"value":"Haverhill, Iowa","data":{"lat":"41.94499","lon":"-92.96075"}},{"value":"Haviland, Ohio","data":{"lat":"41.01894","lon":"-84.58079"}},{"value":"Haviland, Kan.","data":{"lat":"37.61946","lon":"-99.1065"}},{"value":"Havre North, Mont.","data":{"lat":"48.56304","lon":"-109.67098"}},{"value":"Hawesville, Ky.","data":{"lat":"37.90006","lon":"-86.75499"}},{"value":"Hawk Cove, Tex.","data":{"lat":"32.88401","lon":"-96.08108"}},{"value":"Hawk Point, Mo.","data":{"lat":"38.97088","lon":"-91.13126"}},{"value":"Hawk Run, Pa.","data":{"lat":"40.92395","lon":"-78.20612"}},{"value":"Hawkeye, Iowa","data":{"lat":"42.93859","lon":"-91.95017"}},{"value":"Hawkins, Wis.","data":{"lat":"45.51497","lon":"-90.71987"}},{"value":"Hawley, Mass.","data":{"lat":"42.56453","lon":"-72.87787"}},{"value":"Hawley, Tex.","data":{"lat":"32.61206","lon":"-99.81426"}},{"value":"Haworth, Okla.","data":{"lat":"33.8465","lon":"-94.65271"}},{"value":"Hawthorn, Pa.","data":{"lat":"41.02007","lon":"-79.27448"}},{"value":"Haxtun, Colo.","data":{"lat":"40.6411","lon":"-102.62686"}},{"value":"Hay Springs, Neb.","data":{"lat":"42.68386","lon":"-102.6899"}},{"value":"Hayden, Ind.","data":{"lat":"38.98311","lon":"-85.74053"}},{"value":"Hayden, Ala.","data":{"lat":"33.8926","lon":"-86.75777"}},{"value":"Hayden, Ariz.","data":{"lat":"33.00479","lon":"-110.78538"}},{"value":"Hayden Lake, Idaho","data":{"lat":"47.75879","lon":"-116.75686"}},{"value":"Haydenville, Ohio","data":{"lat":"39.48201","lon":"-82.32821"}},{"value":"Hayes, La.","data":{"lat":"30.10882","lon":"-92.92015"}},{"value":"Hayes Center, Neb.","data":{"lat":"40.51084","lon":"-101.0196"}},{"value":"Hayesville, N.C.","data":{"lat":"35.0462","lon":"-83.81795"}},{"value":"Hayesville, Ohio","data":{"lat":"40.77311","lon":"-82.26238"}},{"value":"Haynes, Ark.","data":{"lat":"34.89093","lon":"-90.79206"}},{"value":"Haynesville, Maine","data":{"lat":"45.82617","lon":"-67.99113"}},{"value":"Hayneville, Ala.","data":{"lat":"32.18403","lon":"-86.58025"}},{"value":"Hays, Tex.","data":{"lat":"30.12271","lon":"-97.87223"}},{"value":"Hays, Mont.","data":{"lat":"47.98916","lon":"-108.69432"}},{"value":"Haysi, Va.","data":{"lat":"37.20539","lon":"-82.29403"}},{"value":"Hayti, S.D.","data":{"lat":"44.65719","lon":"-97.20507"}},{"value":"Hayti Heights, Mo.","data":{"lat":"36.23396","lon":"-89.76953"}},{"value":"Hayward, Mo.","data":{"lat":"36.39868","lon":"-89.67008"}},{"value":"Hayward, Minn.","data":{"lat":"43.65051","lon":"-93.24409"}},{"value":"Haywood City, Mo.","data":{"lat":"37.01255","lon":"-89.60147"}},{"value":"Hazel, Ky.","data":{"lat":"36.50228","lon":"-88.32587"}},{"value":"Hazel Green, Ky.","data":{"lat":"37.79759","lon":"-83.41657"}},{"value":"Hazelton, Idaho","data":{"lat":"42.5963","lon":"-114.13614"}},{"value":"Hazelton, N.D.","data":{"lat":"46.48471","lon":"-100.27956"}},{"value":"Hazleton, Iowa","data":{"lat":"42.62082","lon":"-91.90017"}},{"value":"Hazleton, Ind.","data":{"lat":"38.48894","lon":"-87.54169"}},{"value":"Hachita, N.M.","data":{"lat":"31.91815","lon":"-108.32032"}},{"value":"Hackberry, Ariz.","data":{"lat":"35.36916","lon":"-113.72716"}},{"value":"Hadley, Minn.","data":{"lat":"44.00108","lon":"-95.8539"}},{"value":"Hague, N.D.","data":{"lat":"46.0286","lon":"-99.99567"}},{"value":"Hainesburg, N.J.","data":{"lat":"40.9551","lon":"-75.06129"}},{"value":"Haivana Nakya, Ariz.","data":{"lat":"32.00674","lon":"-111.71373"}},{"value":"Halibut Cove, Alaska","data":{"lat":"59.595","lon":"-151.225"}},{"value":"Halma, Minn.","data":{"lat":"48.66109","lon":"-96.60032"}},{"value":"Halsey, Neb.","data":{"lat":"41.90333","lon":"-100.26902"}},{"value":"Hamberg, N.D.","data":{"lat":"47.76306","lon":"-99.51457"}},{"value":"Hamer, Idaho","data":{"lat":"43.92713","lon":"-112.20609"}},{"value":"Hamill, S.D.","data":{"lat":"43.59472","lon":"-99.6815"}},{"value":"Hamilton, N.D.","data":{"lat":"48.8086","lon":"-97.45286"}},{"value":"Hamlet, Neb.","data":{"lat":"40.385","lon":"-101.23461"}},{"value":"Hamletsburg, Ill.","data":{"lat":"37.13867","lon":"-88.43171"}},{"value":"Hamlin, Kan.","data":{"lat":"39.91611","lon":"-95.62804"}},{"value":"Hampden, N.D.","data":{"lat":"48.54028","lon":"-98.65429"}},{"value":"Hannah, N.D.","data":{"lat":"48.97167","lon":"-98.69179"}},{"value":"Hansboro, N.D.","data":{"lat":"48.95001","lon":"-99.38291"}},{"value":"Hansell, Iowa","data":{"lat":"42.75775","lon":"-93.10409"}},{"value":"Harbine, Neb.","data":{"lat":"40.19222","lon":"-96.97253"}},{"value":"Hardy, Iowa","data":{"lat":"42.81053","lon":"-94.05134"}},{"value":"Harris, Kan.","data":{"lat":"38.31946","lon":"-95.43637"}},{"value":"Harris, Mo.","data":{"lat":"40.30585","lon":"-93.35022"}},{"value":"Harrisburg, Neb.","data":{"lat":"41.55636","lon":"-103.73856"}},{"value":"Harrison, S.D.","data":{"lat":"43.42971","lon":"-98.5273"}},{"value":"Hartland, Calif.","data":{"lat":"36.65439","lon":"-118.95761"}},{"value":"Hartly, Del.","data":{"lat":"39.16872","lon":"-75.71326"}},{"value":"Hartman, Colo.","data":{"lat":"38.12029","lon":"-102.21991"}},{"value":"Hartville, Wyo.","data":{"lat":"42.32747","lon":"-104.72524"}},{"value":"Hartwell, Mo.","data":{"lat":"38.4353","lon":"-93.93466"}},{"value":"Hartwick, Iowa","data":{"lat":"41.78472","lon":"-92.34352"}},{"value":"Harwood, Mo.","data":{"lat":"37.95614","lon":"-94.15439"}},{"value":"Hassell, N.C.","data":{"lat":"35.90794","lon":"-77.27858"}},{"value":"Haswell, Colo.","data":{"lat":"38.45223","lon":"-103.16298"}},{"value":"Hatfield, Minn.","data":{"lat":"43.95747","lon":"-96.19531"}},{"value":"Havana, N.D.","data":{"lat":"45.95024","lon":"-97.61899"}},{"value":"Hawk Springs, Wyo.","data":{"lat":"41.78608","lon":"-104.26468"}},{"value":"Hayesville, Iowa","data":{"lat":"41.26446","lon":"-92.24907"}},{"value":"Hayfield, Iowa","data":{"lat":"43.17663","lon":"-93.69522"}},{"value":"Haynes, N.D.","data":{"lat":"45.97417","lon":"-102.47099"}},{"value":"Haysville, Pa.","data":{"lat":"40.52646","lon":"-80.15895"}},{"value":"Haysville, Pa.","data":{"lat":"40.99867","lon":"-79.75449"}},{"value":"Hazard, Neb.","data":{"lat":"41.09057","lon":"-99.07926"}},{"value":"Hazel, S.D.","data":{"lat":"44.75969","lon":"-97.37952"}},{"value":"Hazel Run, Minn.","data":{"lat":"44.7519","lon":"-95.71502"}},{"value":"Hazelton, Kan.","data":{"lat":"37.0903","lon":"-98.39841"}},{"value":"Halls Crossing, Utah","data":{"lat":"37.45694","lon":"-110.71292"}},{"value":"Hanks, N.D.","data":{"lat":"48.60336","lon":"-103.80298"}}]}
